{"timestamp": "2019-Jan-20 15:57:44", "towers": [{"id": 2375, "url": "/building/erastus-corning-ii-tower/2375", "name": "Erastus Corning II Tower", "status": "COM", "height_architecture": 179.53, "longitude": -73.759552, "latitude": 42.649151, "rank": 1, "name_linked": "<a href='/building/erastus-corning-ii-tower/2375' target='_blank'>Erastus Corning II Tower</a>", "country_id": 163, "country_chinese": "", "city_id": 1503, "country_locode": "US", "country_slug": "united-states", "city_locode": "ALB", "city": "Albany", "city_slug": "albany", "height_architecture_formatted": 179.5, "height_architecture_ft_formatted": "589", "floors_above": 44, "completed": 1973, "start": "-", "structural_material": "", "functions": "office", "retrofit_functions": "", "image": ""}, {"id": 9479, "url": "/building/alfred-e-smith-state-office-building/9479", "name": "Alfred E. Smith State Office Building", "status": "COM", "height_architecture": 118.26, "longitude": -73.759773, "latitude": 42.653969, "rank": 2, "name_linked": "<a href='/building/alfred-e-smith-state-office-building/9479' target='_blank'>Alfred E. Smith State Office Building</a>", "country_id": 163, "country_chinese": "", "city_id": 1503, "country_locode": "US", "country_slug": "united-states", "city_locode": "ALB", "city": "Albany", "city_slug": "albany", "height_architecture_formatted": 118.3, "height_architecture_ft_formatted": "388", "floors_above": 34, "completed": 1930, "start": 1927, "structural_material": "steel", "functions": "office", "retrofit_functions": "", "image": ""}, {"id": 12351, "url": "/building/1-empire-state-plaza/12351", "name": "1 Empire State Plaza", "status": "COM", "height_architecture": 94.49, "longitude": -73.759621, "latitude": 42.651718, "rank": 3, "name_linked": "<a href='/building/1-empire-state-plaza/12351' target='_blank'>1 Empire State Plaza</a>", "country_id": 163, "country_chinese": "", "city_id": 1503, "country_locode": "US", "country_slug": "united-states", "city_locode": "ALB", "city": "Albany", "city_slug": "albany", "height_architecture_formatted": 94.5, "height_architecture_ft_formatted": "310", "floors_above": 23, "completed": 1973, "start": "-", "structural_material": "steel", "functions": "government", "retrofit_functions": "", "image": ""}, {"id": 12352, "url": "/building/2-empire-state-plaza/12352", "name": "2 Empire State Plaza", "status": "COM", "height_architecture": 94.49, "longitude": -73.760269, "latitude": 42.651051, "rank": 3, "name_linked": "<a href='/building/2-empire-state-plaza/12352' target='_blank'>2 Empire State Plaza</a>", "country_id": 163, "country_chinese": "", "city_id": 1503, "country_locode": "US", "country_slug": "united-states", "city_locode": "ALB", "city": "Albany", "city_slug": "albany", "height_architecture_formatted": 94.5, "height_architecture_ft_formatted": "310", "floors_above": 23, "completed": 1973, "start": "-", "structural_material": "steel", "functions": "government", "retrofit_functions": "", "image": ""}, {"id": 12353, "url": "/building/3-empire-state-plaza/12353", "name": "3 Empire State Plaza", "status": "COM", "height_architecture": 94.49, "longitude": -73.760971, "latitude": 42.650391, "rank": 3, "name_linked": "<a href='/building/3-empire-state-plaza/12353' target='_blank'>3 Empire State Plaza</a>", "country_id": 163, "country_chinese": "", "city_id": 1503, "country_locode": "US", "country_slug": "united-states", "city_locode": "ALB", "city": "Albany", "city_slug": "albany", "height_architecture_formatted": 94.5, "height_architecture_ft_formatted": "310", "floors_above": 23, "completed": 1973, "start": "-", "structural_material": "steel", "functions": "government", "retrofit_functions": "", "image": ""}, {"id": 12354, "url": "/building/4-empire-state-plaza/12354", "name": "4 Empire State Plaza", "status": "COM", "height_architecture": 94.49, "longitude": -73.76162, "latitude": 42.64975, "rank": 3, "name_linked": "<a href='/building/4-empire-state-plaza/12354' target='_blank'>4 Empire State Plaza</a>", "country_id": 163, "country_chinese": "", "city_id": 1503, "country_locode": "US", "country_slug": "united-states", "city_locode": "ALB", "city": "Albany", "city_slug": "albany", "height_architecture_formatted": 94.5, "height_architecture_ft_formatted": "310", "floors_above": 23, "completed": 1974, "start": "-", "structural_material": "steel", "functions": "government", "retrofit_functions": "", "image": ""}, {"id": 12358, "url": "/building/eastman-tower/12358", "name": "Eastman Tower", "status": "COM", "height_architecture": 87.17, "longitude": -73.820229, "latitude": 42.686771, "rank": 7, "name_linked": "<a href='/building/eastman-tower/12358' target='_blank'>Eastman Tower</a>", "country_id": 163, "country_chinese": "", "city_id": 1503, "country_locode": "US", "country_slug": "united-states", "city_locode": "ALB", "city": "Albany", "city_slug": "albany", "height_architecture_formatted": 87.2, "height_architecture_ft_formatted": "286", "floors_above": 22, "completed": 1967, "start": "-", "structural_material": "", "functions": "residential", "retrofit_functions": "", "image": ""}, {"id": 12357, "url": "/building/livingston-tower/12357", "name": "Livingston Tower", "status": "COM", "height_architecture": 87.17, "longitude": -73.824051, "latitude": 42.689049, "rank": 7, "name_linked": "<a href='/building/livingston-tower/12357' target='_blank'>Livingston Tower</a>", "country_id": 163, "country_chinese": "", "city_id": 1503, "country_locode": "US", "country_slug": "united-states", "city_locode": "ALB", "city": "Albany", "city_slug": "albany", "height_architecture_formatted": 87.2, "height_architecture_ft_formatted": "286", "floors_above": 22, "completed": 1965, "start": "-", "structural_material": "", "functions": "residential", "retrofit_functions": "", "image": ""}, {"id": 12355, "url": "/building/mohawk-tower/12355", "name": "Mohawk Tower", "status": "COM", "height_architecture": 87.17, "longitude": -73.823807, "latitude": 42.68327, "rank": 7, "name_linked": "<a href='/building/mohawk-tower/12355' target='_blank'>Mohawk Tower</a>", "country_id": 163, "country_chinese": "", "city_id": 1503, "country_locode": "US", "country_slug": "united-states", "city_locode": "ALB", "city": "Albany", "city_slug": "albany", "height_architecture_formatted": 87.2, "height_architecture_ft_formatted": "286", "floors_above": 22, "completed": 1972, "start": "-", "structural_material": "", "functions": "residential", "retrofit_functions": "", "image": ""}, {"id": 12356, "url": "/building/stuyvesant-tower/12356", "name": "Stuyvesant Tower", "status": "COM", "height_architecture": 87.17, "longitude": -73.827682, "latitude": 42.68544, "rank": 7, "name_linked": "<a href='/building/stuyvesant-tower/12356' target='_blank'>Stuyvesant Tower</a>", "country_id": 163, "country_chinese": "", "city_id": 1503, "country_locode": "US", "country_slug": "united-states", "city_locode": "ALB", "city": "Albany", "city_slug": "albany", "height_architecture_formatted": 87.2, "height_architecture_ft_formatted": "286", "floors_above": 22, "completed": 1964, "start": "-", "structural_material": "", "functions": "residential", "retrofit_functions": "", "image": ""}, {"id": 12370, "url": "/building/11-north-pearl-street/12370", "name": "11 North Pearl Street", "status": "COM", "height_architecture": 84.12, "longitude": -73.752327, "latitude": 42.650108, "rank": 11, "name_linked": "<a href='/building/11-north-pearl-street/12370' target='_blank'>11 North Pearl Street</a>", "country_id": 163, "country_chinese": "", "city_id": 1503, "country_locode": "US", "country_slug": "united-states", "city_locode": "ALB", "city": "Albany", "city_slug": "albany", "height_architecture_formatted": 84.1, "height_architecture_ft_formatted": "276", "floors_above": 21, "completed": 1927, "start": "-", "structural_material": "", "functions": "office", "retrofit_functions": "", "image": ""}]}