{"timestamp": "2019-Jan-20 15:57:45", "towers": [{"id": 32702, "url": "/building/songda-view-the-world-8/32702", "name": "Songda view the world 8#", "status": "UC", "height_architecture": 200, "longitude": 0, "latitude": 0, "rank": 1, "name_linked": "<a href='/building/songda-view-the-world-8/32702' target='_blank'>Songda view the world 8#</a>", "country_id": 34, "country_chinese": "", "city_id": 2821, "country_locode": "CN", "country_slug": "china", "city_locode": "KWE", "city": "Guigang", "city_slug": "guigang", "height_architecture_formatted": 200, "height_architecture_ft_formatted": "656", "floors_above": 50, "completed": 2020, "start": 2017, "structural_material": "", "functions": "office / hotel", "retrofit_functions": "", "image": ""}, {"id": 31933, "url": "/building/triumph-international-office-a/31933", "name": "Triumph International Office A", "status": "UC", "height_architecture": 149.3, "longitude": 109.562859, "latitude": 23.104822, "rank": 2, "name_linked": "<a href='/building/triumph-international-office-a/31933' target='_blank'>Triumph International Office A</a>", "country_id": 34, "country_chinese": "", "city_id": 2821, "country_locode": "CN", "country_slug": "china", "city_locode": "KWE", "city": "Guigang", "city_slug": "guigang", "height_architecture_formatted": 149.3, "height_architecture_ft_formatted": "490", "floors_above": 32, "completed": 2019, "start": 2016, "structural_material": "", "functions": "office", "retrofit_functions": "", "image": ""}, {"id": 31948, "url": "/building/guigang-golden-age-10/31948", "name": "Guigang Golden Age 10#", "status": "COM", "height_architecture": 140, "longitude": 0, "latitude": 0, "rank": 3, "name_linked": "<a href='/building/guigang-golden-age-10/31948' target='_blank'>Guigang Golden Age 10#</a>", "country_id": 34, "country_chinese": "", "city_id": 2821, "country_locode": "CN", "country_slug": "china", "city_locode": "KWE", "city": "Guigang", "city_slug": "guigang", "height_architecture_formatted": 140, "height_architecture_ft_formatted": "459", "floors_above": 37, "completed": 2013, "start": 2011, "structural_material": "", "functions": "residential", "retrofit_functions": "", "image": ""}, {"id": 31949, "url": "/building/guigang-golden-age-11/31949", "name": "Guigang Golden Age 11#", "status": "COM", "height_architecture": 140, "longitude": 0, "latitude": 0, "rank": 3, "name_linked": "<a href='/building/guigang-golden-age-11/31949' target='_blank'>Guigang Golden Age 11#</a>", "country_id": 34, "country_chinese": "", "city_id": 2821, "country_locode": "CN", "country_slug": "china", "city_locode": "KWE", "city": "Guigang", "city_slug": "guigang", "height_architecture_formatted": 140, "height_architecture_ft_formatted": "459", "floors_above": 37, "completed": 2014, "start": 2012, "structural_material": "", "functions": "residential", "retrofit_functions": "", "image": ""}, {"id": 32441, "url": "/building/spirit-park-view-1/32441", "name": "Spirit Park View 1#", "status": "COM", "height_architecture": 137.8, "longitude": 0, "latitude": 0, "rank": 5, "name_linked": "<a href='/building/spirit-park-view-1/32441' target='_blank'>Spirit Park View 1#</a>", "country_id": 34, "country_chinese": "", "city_id": 2821, "country_locode": "CN", "country_slug": "china", "city_locode": "KWE", "city": "Guigang", "city_slug": "guigang", "height_architecture_formatted": 137.8, "height_architecture_ft_formatted": "452", "floors_above": 40, "completed": 2016, "start": 2013, "structural_material": "concrete", "functions": "residential", "retrofit_functions": "", "image": ""}, {"id": 32442, "url": "/building/spirit-park-view-6/32442", "name": "Spirit Park View 6# ", "status": "COM", "height_architecture": 137.8, "longitude": 0, "latitude": 0, "rank": 5, "name_linked": "<a href='/building/spirit-park-view-6/32442' target='_blank'>Spirit Park View 6# </a>", "country_id": 34, "country_chinese": "", "city_id": 2821, "country_locode": "CN", "country_slug": "china", "city_locode": "KWE", "city": "Guigang", "city_slug": "guigang", "height_architecture_formatted": 137.8, "height_architecture_ft_formatted": "452", "floors_above": 40, "completed": 2016, "start": 2013, "structural_material": "concrete", "functions": "residential", "retrofit_functions": "", "image": ""}, {"id": 32443, "url": "/building/spirit-park-view-2/32443", "name": "Spirit Park View 2# ", "status": "COM", "height_architecture": 131.6, "longitude": 0, "latitude": 0, "rank": 7, "name_linked": "<a href='/building/spirit-park-view-2/32443' target='_blank'>Spirit Park View 2# </a>", "country_id": 34, "country_chinese": "", "city_id": 2821, "country_locode": "CN", "country_slug": "china", "city_locode": "KWE", "city": "Guigang", "city_slug": "guigang", "height_architecture_formatted": 131.6, "height_architecture_ft_formatted": "432", "floors_above": 38, "completed": 2016, "start": 2013, "structural_material": "concrete", "functions": "residential", "retrofit_functions": "", "image": ""}, {"id": 32444, "url": "/building/spirit-park-view-3/32444", "name": "Spirit Park View 3# ", "status": "COM", "height_architecture": 131.6, "longitude": 0, "latitude": 0, "rank": 7, "name_linked": "<a href='/building/spirit-park-view-3/32444' target='_blank'>Spirit Park View 3# </a>", "country_id": 34, "country_chinese": "", "city_id": 2821, "country_locode": "CN", "country_slug": "china", "city_locode": "KWE", "city": "Guigang", "city_slug": "guigang", "height_architecture_formatted": 131.6, "height_architecture_ft_formatted": "432", "floors_above": 38, "completed": 2016, "start": 2013, "structural_material": "concrete", "functions": "residential", "retrofit_functions": "", "image": ""}, {"id": 32446, "url": "/building/spirit-park-view-4/32446", "name": "Spirit Park View 4#", "status": "COM", "height_architecture": 131.6, "longitude": 0, "latitude": 0, "rank": 7, "name_linked": "<a href='/building/spirit-park-view-4/32446' target='_blank'>Spirit Park View 4#</a>", "country_id": 34, "country_chinese": "", "city_id": 2821, "country_locode": "CN", "country_slug": "china", "city_locode": "KWE", "city": "Guigang", "city_slug": "guigang", "height_architecture_formatted": 131.6, "height_architecture_ft_formatted": "432", "floors_above": 38, "completed": 2016, "start": 2013, "structural_material": "concrete", "functions": "residential", "retrofit_functions": "", "image": ""}, {"id": 32447, "url": "/building/spirit-park-view-5/32447", "name": "Spirit Park View 5# ", "status": "COM", "height_architecture": 131.6, "longitude": 0, "latitude": 0, "rank": 7, "name_linked": "<a href='/building/spirit-park-view-5/32447' target='_blank'>Spirit Park View 5# </a>", "country_id": 34, "country_chinese": "", "city_id": 2821, "country_locode": "CN", "country_slug": "china", "city_locode": "KWE", "city": "Guigang", "city_slug": "guigang", "height_architecture_formatted": 131.6, "height_architecture_ft_formatted": "432", "floors_above": 38, "completed": 2016, "start": 2013, "structural_material": "concrete", "functions": "residential", "retrofit_functions": "", "image": ""}, {"id": 31931, "url": "/building/triumph-international-10/31931", "name": "Triumph International 10#", "status": "COM", "height_architecture": 129.9, "longitude": 109.562057, "latitude": 23.104309, "rank": 11, "name_linked": "<a href='/building/triumph-international-10/31931' target='_blank'>Triumph International 10#</a>", "country_id": 34, "country_chinese": "", "city_id": 2821, "country_locode": "CN", "country_slug": "china", "city_locode": "KWE", "city": "Guigang", "city_slug": "guigang", "height_architecture_formatted": 129.9, "height_architecture_ft_formatted": "426", "floors_above": 32, "completed": 2016, "start": 2014, "structural_material": "", "functions": "residential", "retrofit_functions": "", "image": ""}, {"id": 32695, "url": "/building/songda-view-the-world-1/32695", "name": "Songda View The World 1#", "status": "COM", "height_architecture": 127.55, "longitude": 0, "latitude": 0, "rank": 12, "name_linked": "<a href='/building/songda-view-the-world-1/32695' target='_blank'>Songda View The World 1#</a>", "country_id": 34, "country_chinese": "", "city_id": 2821, "country_locode": "CN", "country_slug": "china", "city_locode": "KWE", "city": "Guigang", "city_slug": "guigang", "height_architecture_formatted": 127.6, "height_architecture_ft_formatted": "418", "floors_above": 37, "completed": 2017, "start": 2014, "structural_material": "", "functions": "residential", "retrofit_functions": "", "image": ""}, {"id": 32704, "url": "/building/songda-view-the-world-10/32704", "name": "Songda View The World 10# ", "status": "COM", "height_architecture": 127.55, "longitude": 0, "latitude": 0, "rank": 12, "name_linked": "<a href='/building/songda-view-the-world-10/32704' target='_blank'>Songda View The World 10# </a>", "country_id": 34, "country_chinese": "", "city_id": 2821, "country_locode": "CN", "country_slug": "china", "city_locode": "KWE", "city": "Guigang", "city_slug": "guigang", "height_architecture_formatted": 127.6, "height_architecture_ft_formatted": "418", "floors_above": 37, "completed": 2017, "start": 2014, "structural_material": "", "functions": "residential", "retrofit_functions": "", "image": ""}, {"id": 32705, "url": "/building/songda-view-the-world-11/32705", "name": "Songda View The World 11# ", "status": "COM", "height_architecture": 127.55, "longitude": 0, "latitude": 0, "rank": 12, "name_linked": "<a href='/building/songda-view-the-world-11/32705' target='_blank'>Songda View The World 11# </a>", "country_id": 34, "country_chinese": "", "city_id": 2821, "country_locode": "CN", "country_slug": "china", "city_locode": "KWE", "city": "Guigang", "city_slug": "guigang", "height_architecture_formatted": 127.6, "height_architecture_ft_formatted": "418", "floors_above": 37, "completed": 2017, "start": 2014, "structural_material": "", "functions": "residential", "retrofit_functions": "", "image": ""}, {"id": 32694, "url": "/building/songda-view-the-world-12/32694", "name": "Songda View The World 12#", "status": "COM", "height_architecture": 127.55, "longitude": 0, "latitude": 0, "rank": 12, "name_linked": "<a href='/building/songda-view-the-world-12/32694' target='_blank'>Songda View The World 12#</a>", "country_id": 34, "country_chinese": "", "city_id": 2821, "country_locode": "CN", "country_slug": "china", "city_locode": "KWE", "city": "Guigang", "city_slug": "guigang", "height_architecture_formatted": 127.6, "height_architecture_ft_formatted": "418", "floors_above": 37, "completed": 2017, "start": 2014, "structural_material": "", "functions": "residential", "retrofit_functions": "", "image": ""}, {"id": 32696, "url": "/building/songda-view-the-world-2/32696", "name": "Songda View The World 2# ", "status": "COM", "height_architecture": 127.55, "longitude": 0, "latitude": 0, "rank": 12, "name_linked": "<a href='/building/songda-view-the-world-2/32696' target='_blank'>Songda View The World 2# </a>", "country_id": 34, "country_chinese": "", "city_id": 2821, "country_locode": "CN", "country_slug": "china", "city_locode": "KWE", "city": "Guigang", "city_slug": "guigang", "height_architecture_formatted": 127.6, "height_architecture_ft_formatted": "418", "floors_above": 37, "completed": 2017, "start": 2014, "structural_material": "", "functions": "residential", "retrofit_functions": "", "image": ""}, {"id": 32697, "url": "/building/songda-view-the-world-3/32697", "name": "Songda View The World 3# ", "status": "COM", "height_architecture": 127.55, "longitude": 0, "latitude": 0, "rank": 12, "name_linked": "<a href='/building/songda-view-the-world-3/32697' target='_blank'>Songda View The World 3# </a>", "country_id": 34, "country_chinese": "", "city_id": 2821, "country_locode": "CN", "country_slug": "china", "city_locode": "KWE", "city": "Guigang", "city_slug": "guigang", "height_architecture_formatted": 127.6, "height_architecture_ft_formatted": "418", "floors_above": 37, "completed": 2017, "start": 2014, "structural_material": "", "functions": "residential", "retrofit_functions": "", "image": ""}, {"id": 32698, "url": "/building/songda-view-the-world-4/32698", "name": "Songda View The World 4# ", "status": "COM", "height_architecture": 127.55, "longitude": 0, "latitude": 0, "rank": 12, "name_linked": "<a href='/building/songda-view-the-world-4/32698' target='_blank'>Songda View The World 4# </a>", "country_id": 34, "country_chinese": "", "city_id": 2821, "country_locode": "CN", "country_slug": "china", "city_locode": "KWE", "city": "Guigang", "city_slug": "guigang", "height_architecture_formatted": 127.6, "height_architecture_ft_formatted": "418", "floors_above": 37, "completed": 2017, "start": 2014, "structural_material": "", "functions": "residential", "retrofit_functions": "", "image": ""}, {"id": 32699, "url": "/building/songda-view-the-world-5/32699", "name": "Songda View The World 5# ", "status": "COM", "height_architecture": 127.55, "longitude": 0, "latitude": 0, "rank": 12, "name_linked": "<a href='/building/songda-view-the-world-5/32699' target='_blank'>Songda View The World 5# </a>", "country_id": 34, "country_chinese": "", "city_id": 2821, "country_locode": "CN", "country_slug": "china", "city_locode": "KWE", "city": "Guigang", "city_slug": "guigang", "height_architecture_formatted": 127.6, "height_architecture_ft_formatted": "418", "floors_above": 37, "completed": 2017, "start": 2014, "structural_material": "", "functions": "residential", "retrofit_functions": "", "image": ""}, {"id": 32700, "url": "/building/songda-view-the-world-6/32700", "name": "Songda View The World 6#", "status": "COM", "height_architecture": 127.55, "longitude": 0, "latitude": 0, "rank": 12, "name_linked": "<a href='/building/songda-view-the-world-6/32700' target='_blank'>Songda View The World 6#</a>", "country_id": 34, "country_chinese": "", "city_id": 2821, "country_locode": "CN", "country_slug": "china", "city_locode": "KWE", "city": "Guigang", "city_slug": "guigang", "height_architecture_formatted": 127.6, "height_architecture_ft_formatted": "418", "floors_above": 37, "completed": 2017, "start": 2014, "structural_material": "", "functions": "residential", "retrofit_functions": "", "image": ""}, {"id": 32701, "url": "/building/songda-view-the-world-7/32701", "name": "Songda View The World 7#", "status": "COM", "height_architecture": 127.55, "longitude": 0, "latitude": 0, "rank": 12, "name_linked": "<a href='/building/songda-view-the-world-7/32701' target='_blank'>Songda View The World 7#</a>", "country_id": 34, "country_chinese": "", "city_id": 2821, "country_locode": "CN", "country_slug": "china", "city_locode": "KWE", "city": "Guigang", "city_slug": "guigang", "height_architecture_formatted": 127.6, "height_architecture_ft_formatted": "418", "floors_above": 37, "completed": 2017, "start": 2014, "structural_material": "", "functions": "residential", "retrofit_functions": "", "image": ""}, {"id": 32703, "url": "/building/songda-view-the-world-9/32703", "name": "Songda View The World 9#", "status": "COM", "height_architecture": 127.55, "longitude": 0, "latitude": 0, "rank": 12, "name_linked": "<a href='/building/songda-view-the-world-9/32703' target='_blank'>Songda View The World 9#</a>", "country_id": 34, "country_chinese": "", "city_id": 2821, "country_locode": "CN", "country_slug": "china", "city_locode": "KWE", "city": "Guigang", "city_slug": "guigang", "height_architecture_formatted": 127.6, "height_architecture_ft_formatted": "418", "floors_above": 37, "completed": 2017, "start": 2014, "structural_material": "", "functions": "residential", "retrofit_functions": "", "image": ""}, {"id": 31579, "url": "/building/guigang-marriott-belvedere-c1/31579", "name": "Guigang Marriott Belvedere C1", "status": "COM", "height_architecture": 124.5, "longitude": 109.572197, "latitude": 23.105455, "rank": 23, "name_linked": "<a href='/building/guigang-marriott-belvedere-c1/31579' target='_blank'>Guigang Marriott Belvedere C1</a>", "country_id": 34, "country_chinese": "", "city_id": 2821, "country_locode": "CN", "country_slug": "china", "city_locode": "KWE", "city": "Guigang", "city_slug": "guigang", "height_architecture_formatted": 124.5, "height_architecture_ft_formatted": "408", "floors_above": 39, "completed": 2018, "start": 2014, "structural_material": "", "functions": "residential", "retrofit_functions": "", "image": ""}, {"id": 31580, "url": "/building/guigang-marriott-belvedere-c2/31580", "name": "Guigang Marriott Belvedere C2", "status": "COM", "height_architecture": 124.5, "longitude": 109.572639, "latitude": 23.10549, "rank": 23, "name_linked": "<a href='/building/guigang-marriott-belvedere-c2/31580' target='_blank'>Guigang Marriott Belvedere C2</a>", "country_id": 34, "country_chinese": "", "city_id": 2821, "country_locode": "CN", "country_slug": "china", "city_locode": "KWE", "city": "Guigang", "city_slug": "guigang", "height_architecture_formatted": 124.5, "height_architecture_ft_formatted": "408", "floors_above": 39, "completed": 2018, "start": 2014, "structural_material": "", "functions": "residential", "retrofit_functions": "", "image": ""}, {"id": 31951, "url": "/building/guigang-golden-age-13/31951", "name": "Guigang Golden Age 13#", "status": "COM", "height_architecture": 121, "longitude": 0, "latitude": 0, "rank": 25, "name_linked": "<a href='/building/guigang-golden-age-13/31951' target='_blank'>Guigang Golden Age 13#</a>", "country_id": 34, "country_chinese": "", "city_id": 2821, "country_locode": "CN", "country_slug": "china", "city_locode": "KWE", "city": "Guigang", "city_slug": "guigang", "height_architecture_formatted": 121, "height_architecture_ft_formatted": "397", "floors_above": 32, "completed": 2014, "start": 2012, "structural_material": "", "functions": "residential", "retrofit_functions": "", "image": ""}, {"id": 31954, "url": "/building/guigang-golden-age-16/31954", "name": "Guigang Golden Age 16#", "status": "COM", "height_architecture": 121, "longitude": 0, "latitude": 0, "rank": 25, "name_linked": "<a href='/building/guigang-golden-age-16/31954' target='_blank'>Guigang Golden Age 16#</a>", "country_id": 34, "country_chinese": "", "city_id": 2821, "country_locode": "CN", "country_slug": "china", "city_locode": "KWE", "city": "Guigang", "city_slug": "guigang", "height_architecture_formatted": 121, "height_architecture_ft_formatted": "397", "floors_above": 32, "completed": 2013, "start": 2011, "structural_material": "", "functions": "residential", "retrofit_functions": "", "image": ""}, {"id": 31950, "url": "/building/guigang-golden-age-12/31950", "name": "Guigang Golden Age 12#", "status": "COM", "height_architecture": 113.5, "longitude": 0, "latitude": 0, "rank": 27, "name_linked": "<a href='/building/guigang-golden-age-12/31950' target='_blank'>Guigang Golden Age 12#</a>", "country_id": 34, "country_chinese": "", "city_id": 2821, "country_locode": "CN", "country_slug": "china", "city_locode": "KWE", "city": "Guigang", "city_slug": "guigang", "height_architecture_formatted": 113.5, "height_architecture_ft_formatted": "372", "floors_above": 30, "completed": 2014, "start": 2012, "structural_material": "", "functions": "residential", "retrofit_functions": "", "image": ""}, {"id": 31947, "url": "/building/guigang-golden-age-17/31947", "name": "Guigang Golden Age 17#", "status": "COM", "height_architecture": 113.5, "longitude": 0, "latitude": 0, "rank": 27, "name_linked": "<a href='/building/guigang-golden-age-17/31947' target='_blank'>Guigang Golden Age 17#</a>", "country_id": 34, "country_chinese": "", "city_id": 2821, "country_locode": "CN", "country_slug": "china", "city_locode": "KWE", "city": "Guigang", "city_slug": "guigang", "height_architecture_formatted": 113.5, "height_architecture_ft_formatted": "372", "floors_above": 30, "completed": 2013, "start": 2011, "structural_material": "", "functions": "residential", "retrofit_functions": "", "image": ""}, {"id": 31581, "url": "/building/guigang-marriott-belvedere-c3/31581", "name": "Guigang Marriott Belvedere C3", "status": "COM", "height_architecture": 109, "longitude": 109.57312, "latitude": 23.105495, "rank": 29, "name_linked": "<a href='/building/guigang-marriott-belvedere-c3/31581' target='_blank'>Guigang Marriott Belvedere C3</a>", "country_id": 34, "country_chinese": "", "city_id": 2821, "country_locode": "CN", "country_slug": "china", "city_locode": "KWE", "city": "Guigang", "city_slug": "guigang", "height_architecture_formatted": 109, "height_architecture_ft_formatted": "358", "floors_above": 34, "completed": 2017, "start": 2014, "structural_material": "", "functions": "residential", "retrofit_functions": "", "image": ""}, {"id": 31582, "url": "/building/guigang-marriott-belvedere-c4/31582", "name": "Guigang Marriott Belvedere C4", "status": "COM", "height_architecture": 109, "longitude": 109.573631, "latitude": 23.105495, "rank": 29, "name_linked": "<a href='/building/guigang-marriott-belvedere-c4/31582' target='_blank'>Guigang Marriott Belvedere C4</a>", "country_id": 34, "country_chinese": "", "city_id": 2821, "country_locode": "CN", "country_slug": "china", "city_locode": "KWE", "city": "Guigang", "city_slug": "guigang", "height_architecture_formatted": 109, "height_architecture_ft_formatted": "358", "floors_above": 34, "completed": 2017, "start": 2014, "structural_material": "", "functions": "residential", "retrofit_functions": "", "image": ""}, {"id": 31577, "url": "/building/guigang-marriott-belvedere-c5/31577", "name": "Guigang Marriott Belvedere C5", "status": "COM", "height_architecture": 109, "longitude": 109.573929, "latitude": 23.105495, "rank": 29, "name_linked": "<a href='/building/guigang-marriott-belvedere-c5/31577' target='_blank'>Guigang Marriott Belvedere C5</a>", "country_id": 34, "country_chinese": "", "city_id": 2821, "country_locode": "CN", "country_slug": "china", "city_locode": "KWE", "city": "Guigang", "city_slug": "guigang", "height_architecture_formatted": 109, "height_architecture_ft_formatted": "358", "floors_above": 34, "completed": 2017, "start": 2014, "structural_material": "", "functions": "residential", "retrofit_functions": "", "image": ""}, {"id": 32855, "url": "/building/oriental-paris-office/32855", "name": "Oriental Paris Office", "status": "COM", "height_architecture": 107, "longitude": 0, "latitude": 0, "rank": 32, "name_linked": "<a href='/building/oriental-paris-office/32855' target='_blank'>Oriental Paris Office</a>", "country_id": 34, "country_chinese": "", "city_id": 2821, "country_locode": "CN", "country_slug": "china", "city_locode": "KWE", "city": "Guigang", "city_slug": "guigang", "height_architecture_formatted": 107, "height_architecture_ft_formatted": "351", "floors_above": 27, "completed": 2011, "start": 2009, "structural_material": "", "functions": "office", "retrofit_functions": "", "image": ""}, {"id": 32530, "url": "/building/guigang-bank-of-china-tower/32530", "name": "Guigang Bank of China Tower", "status": "COM", "height_architecture": 105.8, "longitude": 109.592896, "latitude": 23.107382, "rank": 33, "name_linked": "<a href='/building/guigang-bank-of-china-tower/32530' target='_blank'>Guigang Bank of China Tower</a>", "country_id": 34, "country_chinese": "", "city_id": 2821, "country_locode": "CN", "country_slug": "china", "city_locode": "KWE", "city": "Guigang", "city_slug": "guigang", "height_architecture_formatted": 105.8, "height_architecture_ft_formatted": "347", "floors_above": 33, "completed": 2010, "start": 2008, "structural_material": "", "functions": "office", "retrofit_functions": "", "image": ""}, {"id": 32648, "url": "/building/new-greatwall-hotel/32648", "name": "New Greatwall Hotel", "status": "COM", "height_architecture": 105, "longitude": 109.596291, "latitude": 23.117889, "rank": 34, "name_linked": "<a href='/building/new-greatwall-hotel/32648' target='_blank'>New Greatwall Hotel</a>", "country_id": 34, "country_chinese": "", "city_id": 2821, "country_locode": "CN", "country_slug": "china", "city_locode": "KWE", "city": "Guigang", "city_slug": "guigang", "height_architecture_formatted": 105, "height_architecture_ft_formatted": "344", "floors_above": 30, "completed": 2010, "start": 2008, "structural_material": "", "functions": "hotel", "retrofit_functions": "", "image": ""}, {"id": 33063, "url": "/building/guanghuiholy-lake-city-10/33063", "name": "Guanghui\u00b7Holy Lake City #10", "status": "COM", "height_architecture": 103.1, "longitude": 0, "latitude": 0, "rank": 35, "name_linked": "<a href='/building/guanghuiholy-lake-city-10/33063' target='_blank'>Guanghui\u00b7Holy Lake City #10</a>", "country_id": 34, "country_chinese": "", "city_id": 2821, "country_locode": "CN", "country_slug": "china", "city_locode": "GUG", "city": "Guigang", "city_slug": "guigang", "height_architecture_formatted": 103.1, "height_architecture_ft_formatted": "338", "floors_above": 33, "completed": 2015, "start": 2013, "structural_material": "", "functions": "residential", "retrofit_functions": "", "image": ""}, {"id": 33064, "url": "/building/guanghuiholy-lake-city-11/33064", "name": "Guanghui\u00b7Holy Lake City #11", "status": "COM", "height_architecture": 103.1, "longitude": 0, "latitude": 0, "rank": 35, "name_linked": "<a href='/building/guanghuiholy-lake-city-11/33064' target='_blank'>Guanghui\u00b7Holy Lake City #11</a>", "country_id": 34, "country_chinese": "", "city_id": 2821, "country_locode": "CN", "country_slug": "china", "city_locode": "GUG", "city": "Guigang", "city_slug": "guigang", "height_architecture_formatted": 103.1, "height_architecture_ft_formatted": "338", "floors_above": 33, "completed": 2015, "start": 2013, "structural_material": "", "functions": "residential", "retrofit_functions": "", "image": ""}, {"id": 33070, "url": "/building/guanghuiholy-lake-city-22/33070", "name": "Guanghui\u00b7Holy Lake City #22", "status": "UC", "height_architecture": 103.1, "longitude": 0, "latitude": 0, "rank": 35, "name_linked": "<a href='/building/guanghuiholy-lake-city-22/33070' target='_blank'>Guanghui\u00b7Holy Lake City #22</a>", "country_id": 34, "country_chinese": "", "city_id": 2821, "country_locode": "CN", "country_slug": "china", "city_locode": "GUG", "city": "Guigang", "city_slug": "guigang", "height_architecture_formatted": 103.1, "height_architecture_ft_formatted": "338", "floors_above": 33, "completed": 2019, "start": 2017, "structural_material": "", "functions": "residential", "retrofit_functions": "", "image": ""}, {"id": 33065, "url": "/building/guanghuiholy-lake-city-8/33065", "name": "Guanghui\u00b7Holy Lake City #8", "status": "COM", "height_architecture": 103.1, "longitude": 0, "latitude": 0, "rank": 35, "name_linked": "<a href='/building/guanghuiholy-lake-city-8/33065' target='_blank'>Guanghui\u00b7Holy Lake City #8</a>", "country_id": 34, "country_chinese": "", "city_id": 2821, "country_locode": "CN", "country_slug": "china", "city_locode": "GUG", "city": "Guigang", "city_slug": "guigang", "height_architecture_formatted": 103.1, "height_architecture_ft_formatted": "338", "floors_above": 33, "completed": 2017, "start": 2015, "structural_material": "", "functions": "residential", "retrofit_functions": "", "image": ""}, {"id": 33066, "url": "/building/guanghuiholy-lake-city-9/33066", "name": "Guanghui\u00b7Holy Lake City 9#", "status": "COM", "height_architecture": 103.1, "longitude": 0, "latitude": 0, "rank": 35, "name_linked": "<a href='/building/guanghuiholy-lake-city-9/33066' target='_blank'>Guanghui\u00b7Holy Lake City 9#</a>", "country_id": 34, "country_chinese": "", "city_id": 2821, "country_locode": "CN", "country_slug": "china", "city_locode": "GUG", "city": "Guigang", "city_slug": "guigang", "height_architecture_formatted": 103.1, "height_architecture_ft_formatted": "338", "floors_above": 33, "completed": 2017, "start": 2015, "structural_material": "", "functions": "residential", "retrofit_functions": "", "image": ""}, {"id": 31952, "url": "/building/guigang-golden-age-14/31952", "name": "Guigang Golden Age 14#", "status": "COM", "height_architecture": 102, "longitude": 0, "latitude": 0, "rank": 40, "name_linked": "<a href='/building/guigang-golden-age-14/31952' target='_blank'>Guigang Golden Age 14#</a>", "country_id": 34, "country_chinese": "", "city_id": 2821, "country_locode": "CN", "country_slug": "china", "city_locode": "KWE", "city": "Guigang", "city_slug": "guigang", "height_architecture_formatted": 102, "height_architecture_ft_formatted": "335", "floors_above": 27, "completed": 2014, "start": 2012, "structural_material": "", "functions": "residential", "retrofit_functions": "", "image": ""}, {"id": 31953, "url": "/building/guigang-golden-age-15/31953", "name": "Guigang Golden Age 15#", "status": "COM", "height_architecture": 102, "longitude": 0, "latitude": 0, "rank": 40, "name_linked": "<a href='/building/guigang-golden-age-15/31953' target='_blank'>Guigang Golden Age 15#</a>", "country_id": 34, "country_chinese": "", "city_id": 2821, "country_locode": "CN", "country_slug": "china", "city_locode": "KWE", "city": "Guigang", "city_slug": "guigang", "height_architecture_formatted": 102, "height_architecture_ft_formatted": "335", "floors_above": 27, "completed": 2013, "start": 2011, "structural_material": "", "functions": "residential", "retrofit_functions": "", "image": ""}, {"id": 32739, "url": "/building/golden-age-dutch-city-a-1-area-5/32739", "name": "Golden Age Dutch City A-1 Area #5", "status": "COM", "height_architecture": 99.9, "longitude": 0, "latitude": 0, "rank": 42, "name_linked": "<a href='/building/golden-age-dutch-city-a-1-area-5/32739' target='_blank'>Golden Age Dutch City A-1 Area #5</a>", "country_id": 34, "country_chinese": "", "city_id": 2821, "country_locode": "CN", "country_slug": "china", "city_locode": "KWE", "city": "Guigang", "city_slug": "guigang", "height_architecture_formatted": 99.9, "height_architecture_ft_formatted": "328", "floors_above": 33, "completed": 2018, "start": 2016, "structural_material": "", "functions": "residential", "retrofit_functions": "", "image": ""}, {"id": 32740, "url": "/building/golden-age-dutch-city-a-1-area-6/32740", "name": "Golden Age Dutch City A-1 Area #6", "status": "COM", "height_architecture": 99.9, "longitude": 0, "latitude": 0, "rank": 42, "name_linked": "<a href='/building/golden-age-dutch-city-a-1-area-6/32740' target='_blank'>Golden Age Dutch City A-1 Area #6</a>", "country_id": 34, "country_chinese": "", "city_id": 2821, "country_locode": "CN", "country_slug": "china", "city_locode": "KWE", "city": "Guigang", "city_slug": "guigang", "height_architecture_formatted": 99.9, "height_architecture_ft_formatted": "328", "floors_above": 33, "completed": 2018, "start": 2016, "structural_material": "", "functions": "residential", "retrofit_functions": "", "image": ""}, {"id": 32742, "url": "/building/golden-age-dutch-city-a-1-area-8/32742", "name": "Golden Age Dutch City A-1 Area #8", "status": "COM", "height_architecture": 99.9, "longitude": 0, "latitude": 0, "rank": 42, "name_linked": "<a href='/building/golden-age-dutch-city-a-1-area-8/32742' target='_blank'>Golden Age Dutch City A-1 Area #8</a>", "country_id": 34, "country_chinese": "", "city_id": 2821, "country_locode": "CN", "country_slug": "china", "city_locode": "KWE", "city": "Guigang", "city_slug": "guigang", "height_architecture_formatted": 99.9, "height_architecture_ft_formatted": "328", "floors_above": 33, "completed": 2018, "start": 2016, "structural_material": "", "functions": "residential", "retrofit_functions": "", "image": ""}, {"id": 32735, "url": "/building/golden-age-dutch-city-a-1-area-1/32735", "name": "Golden Age Dutch City A-1 Area #1", "status": "COM", "height_architecture": 99.9, "longitude": 0, "latitude": 0, "rank": 45, "name_linked": "<a href='/building/golden-age-dutch-city-a-1-area-1/32735' target='_blank'>Golden Age Dutch City A-1 Area #1</a>", "country_id": 34, "country_chinese": "", "city_id": 2821, "country_locode": "CN", "country_slug": "china", "city_locode": "GUG", "city": "Guigang", "city_slug": "guigang", "height_architecture_formatted": 99.9, "height_architecture_ft_formatted": "328", "floors_above": 32, "completed": 2018, "start": 2016, "structural_material": "", "functions": "residential", "retrofit_functions": "", "image": ""}, {"id": 32737, "url": "/building/golden-age-dutch-city-a-1-area-2/32737", "name": "Golden Age Dutch City A-1 Area #2 ", "status": "COM", "height_architecture": 99.9, "longitude": 0, "latitude": 0, "rank": 45, "name_linked": "<a href='/building/golden-age-dutch-city-a-1-area-2/32737' target='_blank'>Golden Age Dutch City A-1 Area #2 </a>", "country_id": 34, "country_chinese": "", "city_id": 2821, "country_locode": "CN", "country_slug": "china", "city_locode": "KWE", "city": "Guigang", "city_slug": "guigang", "height_architecture_formatted": 99.9, "height_architecture_ft_formatted": "328", "floors_above": 32, "completed": 2018, "start": 2016, "structural_material": "", "functions": "residential", "retrofit_functions": "", "image": ""}, {"id": 32747, "url": "/building/golden-age-dutch-city-a-3-area-1/32747", "name": "Golden Age Dutch City A-3 Area #1", "status": "COM", "height_architecture": 99.9, "longitude": 0, "latitude": 0, "rank": 45, "name_linked": "<a href='/building/golden-age-dutch-city-a-3-area-1/32747' target='_blank'>Golden Age Dutch City A-3 Area #1</a>", "country_id": 34, "country_chinese": "", "city_id": 2821, "country_locode": "CN", "country_slug": "china", "city_locode": "KWE", "city": "Guigang", "city_slug": "guigang", "height_architecture_formatted": 99.9, "height_architecture_ft_formatted": "328", "floors_above": 32, "completed": 2017, "start": 2015, "structural_material": "", "functions": "residential", "retrofit_functions": "", "image": ""}, {"id": 32748, "url": "/building/golden-age-dutch-city-a-3-area-2/32748", "name": "Golden Age Dutch City A-3 Area #2  ", "status": "COM", "height_architecture": 99.9, "longitude": 0, "latitude": 0, "rank": 45, "name_linked": "<a href='/building/golden-age-dutch-city-a-3-area-2/32748' target='_blank'>Golden Age Dutch City A-3 Area #2  </a>", "country_id": 34, "country_chinese": "", "city_id": 2821, "country_locode": "CN", "country_slug": "china", "city_locode": "KWE", "city": "Guigang", "city_slug": "guigang", "height_architecture_formatted": 99.9, "height_architecture_ft_formatted": "328", "floors_above": 32, "completed": 2017, "start": 2015, "structural_material": "", "functions": "residential", "retrofit_functions": "", "image": ""}, {"id": 32736, "url": "/building/golden-age-dutch-city-a-3-area-3/32736", "name": "Golden Age Dutch City A-3 Area #3", "status": "COM", "height_architecture": 99.9, "longitude": 0, "latitude": 0, "rank": 45, "name_linked": "<a href='/building/golden-age-dutch-city-a-3-area-3/32736' target='_blank'>Golden Age Dutch City A-3 Area #3</a>", "country_id": 34, "country_chinese": "", "city_id": 2821, "country_locode": "CN", "country_slug": "china", "city_locode": "KWE", "city": "Guigang", "city_slug": "guigang", "height_architecture_formatted": 99.9, "height_architecture_ft_formatted": "328", "floors_above": 32, "completed": 2017, "start": 2015, "structural_material": "", "functions": "residential", "retrofit_functions": "", "image": ""}, {"id": 33521, "url": "/building/triumph-international-1/33521", "name": "Triumph International 1#", "status": "UC", "height_architecture": 99.9, "longitude": 109.56057, "latitude": 23.105619, "rank": 45, "name_linked": "<a href='/building/triumph-international-1/33521' target='_blank'>Triumph International 1#</a>", "country_id": 34, "country_chinese": "", "city_id": 2821, "country_locode": "CN", "country_slug": "china", "city_locode": "KWE", "city": "Guigang", "city_slug": "guigang", "height_architecture_formatted": 99.9, "height_architecture_ft_formatted": "328", "floors_above": 32, "completed": 2020, "start": 2018, "structural_material": "", "functions": "residential", "retrofit_functions": "", "image": ""}, {"id": 31936, "url": "/building/triumph-international-13/31936", "name": "Triumph International 13#", "status": "COM", "height_architecture": 99.9, "longitude": 109.560242, "latitude": 23.103294, "rank": 45, "name_linked": "<a href='/building/triumph-international-13/31936' target='_blank'>Triumph International 13#</a>", "country_id": 34, "country_chinese": "", "city_id": 2821, "country_locode": "CN", "country_slug": "china", "city_locode": "KWE", "city": "Guigang", "city_slug": "guigang", "height_architecture_formatted": 99.9, "height_architecture_ft_formatted": "328", "floors_above": 32, "completed": 2018, "start": 2016, "structural_material": "", "functions": "residential", "retrofit_functions": "", "image": ""}, {"id": 31937, "url": "/building/triumph-international-15/31937", "name": "Triumph International 15#", "status": "COM", "height_architecture": 99.9, "longitude": 109.561035, "latitude": 23.103357, "rank": 45, "name_linked": "<a href='/building/triumph-international-15/31937' target='_blank'>Triumph International 15#</a>", "country_id": 34, "country_chinese": "", "city_id": 2821, "country_locode": "CN", "country_slug": "china", "city_locode": "KWE", "city": "Guigang", "city_slug": "guigang", "height_architecture_formatted": 99.9, "height_architecture_ft_formatted": "328", "floors_above": 32, "completed": 2018, "start": 2016, "structural_material": "", "functions": "residential", "retrofit_functions": "", "image": ""}, {"id": 33522, "url": "/building/triumph-international-2/33522", "name": "Triumph International 2#", "status": "UC", "height_architecture": 99.9, "longitude": 109.561218, "latitude": 23.105623, "rank": 45, "name_linked": "<a href='/building/triumph-international-2/33522' target='_blank'>Triumph International 2#</a>", "country_id": 34, "country_chinese": "", "city_id": 2821, "country_locode": "CN", "country_slug": "china", "city_locode": "KWE", "city": "Guigang", "city_slug": "guigang", "height_architecture_formatted": 99.9, "height_architecture_ft_formatted": "328", "floors_above": 32, "completed": 2020, "start": 2018, "structural_material": "", "functions": "residential", "retrofit_functions": "", "image": ""}, {"id": 33523, "url": "/building/triumph-international-3/33523", "name": "Triumph International 3#", "status": "UC", "height_architecture": 99.9, "longitude": 109.561783, "latitude": 23.105524, "rank": 45, "name_linked": "<a href='/building/triumph-international-3/33523' target='_blank'>Triumph International 3#</a>", "country_id": 34, "country_chinese": "", "city_id": 2821, "country_locode": "CN", "country_slug": "china", "city_locode": "KWE", "city": "Guigang", "city_slug": "guigang", "height_architecture_formatted": 99.9, "height_architecture_ft_formatted": "328", "floors_above": 32, "completed": 2020, "start": 2018, "structural_material": "", "functions": "residential", "retrofit_functions": "", "image": ""}, {"id": 33518, "url": "/building/triumph-international-5/33518", "name": "Triumph International 5#", "status": "UC", "height_architecture": 99.9, "longitude": 109.560532, "latitude": 23.104784, "rank": 45, "name_linked": "<a href='/building/triumph-international-5/33518' target='_blank'>Triumph International 5#</a>", "country_id": 34, "country_chinese": "", "city_id": 2821, "country_locode": "CN", "country_slug": "china", "city_locode": "KWE", "city": "Guigang", "city_slug": "guigang", "height_architecture_formatted": 99.9, "height_architecture_ft_formatted": "328", "floors_above": 32, "completed": 2020, "start": 2018, "structural_material": "", "functions": "residential", "retrofit_functions": "", "image": ""}, {"id": 33519, "url": "/building/triumph-international-6/33519", "name": "Triumph International 6#", "status": "UC", "height_architecture": 99.9, "longitude": 109.561188, "latitude": 23.104815, "rank": 45, "name_linked": "<a href='/building/triumph-international-6/33519' target='_blank'>Triumph International 6#</a>", "country_id": 34, "country_chinese": "", "city_id": 2821, "country_locode": "CN", "country_slug": "china", "city_locode": "KWE", "city": "Guigang", "city_slug": "guigang", "height_architecture_formatted": 99.9, "height_architecture_ft_formatted": "328", "floors_above": 32, "completed": 2020, "start": 2018, "structural_material": "", "functions": "residential", "retrofit_functions": "", "image": ""}, {"id": 33520, "url": "/building/triumph-international-7/33520", "name": "Triumph International 7#", "status": "UC", "height_architecture": 99.9, "longitude": 109.561897, "latitude": 23.104958, "rank": 45, "name_linked": "<a href='/building/triumph-international-7/33520' target='_blank'>Triumph International 7#</a>", "country_id": 34, "country_chinese": "", "city_id": 2821, "country_locode": "CN", "country_slug": "china", "city_locode": "KWE", "city": "Guigang", "city_slug": "guigang", "height_architecture_formatted": 99.9, "height_architecture_ft_formatted": "328", "floors_above": 32, "completed": 2020, "start": 2018, "structural_material": "", "functions": "residential", "retrofit_functions": "", "image": ""}, {"id": 31941, "url": "/building/triumph-international-8/31941", "name": "Triumph International 8#", "status": "COM", "height_architecture": 99.9, "longitude": 109.560432, "latitude": 23.104172, "rank": 45, "name_linked": "<a href='/building/triumph-international-8/31941' target='_blank'>Triumph International 8#</a>", "country_id": 34, "country_chinese": "", "city_id": 2821, "country_locode": "CN", "country_slug": "china", "city_locode": "KWE", "city": "Guigang", "city_slug": "guigang", "height_architecture_formatted": 99.9, "height_architecture_ft_formatted": "328", "floors_above": 32, "completed": 2018, "start": 2016, "structural_material": "", "functions": "residential", "retrofit_functions": "", "image": ""}, {"id": 31940, "url": "/building/triumph-international-9/31940", "name": "Triumph International 9#", "status": "COM", "height_architecture": 99.9, "longitude": 109.561104, "latitude": 23.104156, "rank": 45, "name_linked": "<a href='/building/triumph-international-9/31940' target='_blank'>Triumph International 9#</a>", "country_id": 34, "country_chinese": "", "city_id": 2821, "country_locode": "CN", "country_slug": "china", "city_locode": "KWE", "city": "Guigang", "city_slug": "guigang", "height_architecture_formatted": 99.9, "height_architecture_ft_formatted": "328", "floors_above": 32, "completed": 2018, "start": 2016, "structural_material": "", "functions": "residential", "retrofit_functions": "", "image": ""}, {"id": 31969, "url": "/building/tian-yue-shangcheng-11/31969", "name": "Tian Yue Shangcheng 11#", "status": "COM", "height_architecture": 99.9, "longitude": 0, "latitude": 0, "rank": 60, "name_linked": "<a href='/building/tian-yue-shangcheng-11/31969' target='_blank'>Tian Yue Shangcheng 11#</a>", "country_id": 34, "country_chinese": "", "city_id": 2821, "country_locode": "CN", "country_slug": "china", "city_locode": "KWE", "city": "Guigang", "city_slug": "guigang", "height_architecture_formatted": 99.9, "height_architecture_ft_formatted": "328", "floors_above": 31, "completed": 2014, "start": "-", "structural_material": "", "functions": "residential", "retrofit_functions": "", "image": ""}, {"id": 31970, "url": "/building/tian-yue-shangcheng-12/31970", "name": "Tian Yue Shangcheng 12#", "status": "COM", "height_architecture": 99.9, "longitude": 0, "latitude": 0, "rank": 60, "name_linked": "<a href='/building/tian-yue-shangcheng-12/31970' target='_blank'>Tian Yue Shangcheng 12#</a>", "country_id": 34, "country_chinese": "", "city_id": 2821, "country_locode": "CN", "country_slug": "china", "city_locode": "KWE", "city": "Guigang", "city_slug": "guigang", "height_architecture_formatted": 99.9, "height_architecture_ft_formatted": "328", "floors_above": 31, "completed": 2014, "start": "-", "structural_material": "", "functions": "residential", "retrofit_functions": "", "image": ""}, {"id": 31958, "url": "/building/tian-yue-shangcheng-1a/31958", "name": "Tian Yue Shangcheng 1A#", "status": "COM", "height_architecture": 99.9, "longitude": 0, "latitude": 0, "rank": 60, "name_linked": "<a href='/building/tian-yue-shangcheng-1a/31958' target='_blank'>Tian Yue Shangcheng 1A#</a>", "country_id": 34, "country_chinese": "", "city_id": 2821, "country_locode": "CN", "country_slug": "china", "city_locode": "KWE", "city": "Guigang", "city_slug": "guigang", "height_architecture_formatted": 99.9, "height_architecture_ft_formatted": "328", "floors_above": 31, "completed": 2015, "start": "-", "structural_material": "", "functions": "residential", "retrofit_functions": "", "image": ""}, {"id": 31960, "url": "/building/tian-yue-shangcheng-1b/31960", "name": "Tian Yue Shangcheng 1B#", "status": "COM", "height_architecture": 99.9, "longitude": 0, "latitude": 0, "rank": 60, "name_linked": "<a href='/building/tian-yue-shangcheng-1b/31960' target='_blank'>Tian Yue Shangcheng 1B#</a>", "country_id": 34, "country_chinese": "", "city_id": 2821, "country_locode": "CN", "country_slug": "china", "city_locode": "KWE", "city": "Guigang", "city_slug": "guigang", "height_architecture_formatted": 99.9, "height_architecture_ft_formatted": "328", "floors_above": 31, "completed": 2015, "start": "-", "structural_material": "", "functions": "residential", "retrofit_functions": "", "image": ""}, {"id": 31962, "url": "/building/tian-yue-shangcheng-3/31962", "name": "Tian Yue Shangcheng 3#", "status": "COM", "height_architecture": 99.9, "longitude": 0, "latitude": 0, "rank": 60, "name_linked": "<a href='/building/tian-yue-shangcheng-3/31962' target='_blank'>Tian Yue Shangcheng 3#</a>", "country_id": 34, "country_chinese": "", "city_id": 2821, "country_locode": "CN", "country_slug": "china", "city_locode": "KWE", "city": "Guigang", "city_slug": "guigang", "height_architecture_formatted": 99.9, "height_architecture_ft_formatted": "328", "floors_above": 31, "completed": 2014, "start": "-", "structural_material": "", "functions": "residential", "retrofit_functions": "", "image": ""}, {"id": 31963, "url": "/building/tian-yue-shangcheng-5/31963", "name": "Tian Yue Shangcheng 5#", "status": "COM", "height_architecture": 99.9, "longitude": 0, "latitude": 0, "rank": 60, "name_linked": "<a href='/building/tian-yue-shangcheng-5/31963' target='_blank'>Tian Yue Shangcheng 5#</a>", "country_id": 34, "country_chinese": "", "city_id": 2821, "country_locode": "CN", "country_slug": "china", "city_locode": "KWE", "city": "Guigang", "city_slug": "guigang", "height_architecture_formatted": 99.9, "height_architecture_ft_formatted": "328", "floors_above": 31, "completed": 2014, "start": "-", "structural_material": "", "functions": "residential", "retrofit_functions": "", "image": ""}, {"id": 31964, "url": "/building/tian-yue-shangcheng-6/31964", "name": "Tian Yue Shangcheng 6#", "status": "COM", "height_architecture": 99.9, "longitude": 0, "latitude": 0, "rank": 60, "name_linked": "<a href='/building/tian-yue-shangcheng-6/31964' target='_blank'>Tian Yue Shangcheng 6#</a>", "country_id": 34, "country_chinese": "", "city_id": 2821, "country_locode": "CN", "country_slug": "china", "city_locode": "KWE", "city": "Guigang", "city_slug": "guigang", "height_architecture_formatted": 99.9, "height_architecture_ft_formatted": "328", "floors_above": 31, "completed": 2014, "start": "-", "structural_material": "", "functions": "residential", "retrofit_functions": "", "image": ""}, {"id": 31965, "url": "/building/tian-yue-shangcheng-7/31965", "name": "Tian Yue Shangcheng 7#", "status": "COM", "height_architecture": 99.9, "longitude": 0, "latitude": 0, "rank": 60, "name_linked": "<a href='/building/tian-yue-shangcheng-7/31965' target='_blank'>Tian Yue Shangcheng 7#</a>", "country_id": 34, "country_chinese": "", "city_id": 2821, "country_locode": "CN", "country_slug": "china", "city_locode": "KWE", "city": "Guigang", "city_slug": "guigang", "height_architecture_formatted": 99.9, "height_architecture_ft_formatted": "328", "floors_above": 31, "completed": 2015, "start": "-", "structural_material": "", "functions": "residential", "retrofit_functions": "", "image": ""}, {"id": 31966, "url": "/building/tian-yue-shangcheng-8/31966", "name": "Tian Yue Shangcheng 8#", "status": "COM", "height_architecture": 99.9, "longitude": 0, "latitude": 0, "rank": 60, "name_linked": "<a href='/building/tian-yue-shangcheng-8/31966' target='_blank'>Tian Yue Shangcheng 8#</a>", "country_id": 34, "country_chinese": "", "city_id": 2821, "country_locode": "CN", "country_slug": "china", "city_locode": "KWE", "city": "Guigang", "city_slug": "guigang", "height_architecture_formatted": 99.9, "height_architecture_ft_formatted": "328", "floors_above": 31, "completed": 2014, "start": "-", "structural_material": "", "functions": "residential", "retrofit_functions": "", "image": ""}, {"id": 31967, "url": "/building/tian-yue-shangcheng-9/31967", "name": "Tian Yue Shangcheng 9#", "status": "COM", "height_architecture": 99.9, "longitude": 0, "latitude": 0, "rank": 60, "name_linked": "<a href='/building/tian-yue-shangcheng-9/31967' target='_blank'>Tian Yue Shangcheng 9#</a>", "country_id": 34, "country_chinese": "", "city_id": 2821, "country_locode": "CN", "country_slug": "china", "city_locode": "KWE", "city": "Guigang", "city_slug": "guigang", "height_architecture_formatted": 99.9, "height_architecture_ft_formatted": "328", "floors_above": 31, "completed": 2014, "start": "-", "structural_material": "", "functions": "residential", "retrofit_functions": "", "image": ""}, {"id": 32548, "url": "/building/elysee-wutai-4/32548", "name": "Elysee Wutai 4#", "status": "UCT", "height_architecture": 99.8, "longitude": 0, "latitude": 0, "rank": 70, "name_linked": "<a href='/building/elysee-wutai-4/32548' target='_blank'>Elysee Wutai 4#</a>", "country_id": 34, "country_chinese": "", "city_id": 2821, "country_locode": "CN", "country_slug": "china", "city_locode": "KWE", "city": "Guigang", "city_slug": "guigang", "height_architecture_formatted": 99.8, "height_architecture_ft_formatted": "327", "floors_above": 32, "completed": 2018, "start": 2016, "structural_material": "", "functions": "residential", "retrofit_functions": "", "image": ""}, {"id": 32550, "url": "/building/elysee-wutai-6/32550", "name": "Elysee Wutai 6#", "status": "UCT", "height_architecture": 99.8, "longitude": 0, "latitude": 0, "rank": 70, "name_linked": "<a href='/building/elysee-wutai-6/32550' target='_blank'>Elysee Wutai 6#</a>", "country_id": 34, "country_chinese": "", "city_id": 2821, "country_locode": "CN", "country_slug": "china", "city_locode": "KWE", "city": "Guigang", "city_slug": "guigang", "height_architecture_formatted": 99.8, "height_architecture_ft_formatted": "327", "floors_above": 32, "completed": 2018, "start": 2016, "structural_material": "", "functions": "residential", "retrofit_functions": "", "image": ""}, {"id": 32551, "url": "/building/elysee-wutai-7/32551", "name": "Elysee Wutai 7#", "status": "UC", "height_architecture": 99.8, "longitude": 0, "latitude": 0, "rank": 70, "name_linked": "<a href='/building/elysee-wutai-7/32551' target='_blank'>Elysee Wutai 7#</a>", "country_id": 34, "country_chinese": "", "city_id": 2821, "country_locode": "CN", "country_slug": "china", "city_locode": "KWE", "city": "Guigang", "city_slug": "guigang", "height_architecture_formatted": 99.8, "height_architecture_ft_formatted": "327", "floors_above": 32, "completed": 2020, "start": 2018, "structural_material": "", "functions": "residential", "retrofit_functions": "", "image": ""}, {"id": 32552, "url": "/building/elysee-wutai-8/32552", "name": "Elysee Wutai 8#", "status": "UC", "height_architecture": 99.8, "longitude": 0, "latitude": 0, "rank": 70, "name_linked": "<a href='/building/elysee-wutai-8/32552' target='_blank'>Elysee Wutai 8#</a>", "country_id": 34, "country_chinese": "", "city_id": 2821, "country_locode": "CN", "country_slug": "china", "city_locode": "KWE", "city": "Guigang", "city_slug": "guigang", "height_architecture_formatted": 99.8, "height_architecture_ft_formatted": "327", "floors_above": 32, "completed": 2020, "start": 2018, "structural_material": "", "functions": "residential", "retrofit_functions": "", "image": ""}, {"id": 31934, "url": "/building/triumph-international-11/31934", "name": "Triumph International 11#", "status": "COM", "height_architecture": 99.7, "longitude": 109.562576, "latitude": 23.10424, "rank": 74, "name_linked": "<a href='/building/triumph-international-11/31934' target='_blank'>Triumph International 11#</a>", "country_id": 34, "country_chinese": "", "city_id": 2821, "country_locode": "CN", "country_slug": "china", "city_locode": "KWE", "city": "Guigang", "city_slug": "guigang", "height_architecture_formatted": 99.7, "height_architecture_ft_formatted": "327", "floors_above": 32, "completed": 2016, "start": 2014, "structural_material": "", "functions": "residential", "retrofit_functions": "", "image": ""}, {"id": 31935, "url": "/building/triumph-international-12/31935", "name": "Triumph International 12#", "status": "COM", "height_architecture": 99.7, "longitude": 109.562996, "latitude": 23.104237, "rank": 74, "name_linked": "<a href='/building/triumph-international-12/31935' target='_blank'>Triumph International 12#</a>", "country_id": 34, "country_chinese": "", "city_id": 2821, "country_locode": "CN", "country_slug": "china", "city_locode": "KWE", "city": "Guigang", "city_slug": "guigang", "height_architecture_formatted": 99.7, "height_architecture_ft_formatted": "327", "floors_above": 32, "completed": 2016, "start": 2014, "structural_material": "", "functions": "residential", "retrofit_functions": "", "image": ""}, {"id": 31938, "url": "/building/triumph-international-16/31938", "name": "Triumph International 16#", "status": "COM", "height_architecture": 99.7, "longitude": 109.562103, "latitude": 23.103437, "rank": 74, "name_linked": "<a href='/building/triumph-international-16/31938' target='_blank'>Triumph International 16#</a>", "country_id": 34, "country_chinese": "", "city_id": 2821, "country_locode": "CN", "country_slug": "china", "city_locode": "KWE", "city": "Guigang", "city_slug": "guigang", "height_architecture_formatted": 99.7, "height_architecture_ft_formatted": "327", "floors_above": 32, "completed": 2016, "start": 2014, "structural_material": "", "functions": "residential", "retrofit_functions": "", "image": ""}, {"id": 31939, "url": "/building/triumph-international-17/31939", "name": "Triumph International 17#", "status": "COM", "height_architecture": 99.7, "longitude": 109.562904, "latitude": 23.103481, "rank": 74, "name_linked": "<a href='/building/triumph-international-17/31939' target='_blank'>Triumph International 17#</a>", "country_id": 34, "country_chinese": "", "city_id": 2821, "country_locode": "CN", "country_slug": "china", "city_locode": "KWE", "city": "Guigang", "city_slug": "guigang", "height_architecture_formatted": 99.7, "height_architecture_ft_formatted": "327", "floors_above": 32, "completed": 2016, "start": 2014, "structural_material": "", "functions": "residential", "retrofit_functions": "", "image": ""}, {"id": 31971, "url": "/building/tian-yue-shangcheng-13/31971", "name": "Tian Yue Shangcheng 13#", "status": "COM", "height_architecture": 99.6, "longitude": 0, "latitude": 0, "rank": 78, "name_linked": "<a href='/building/tian-yue-shangcheng-13/31971' target='_blank'>Tian Yue Shangcheng 13#</a>", "country_id": 34, "country_chinese": "", "city_id": 2821, "country_locode": "CN", "country_slug": "china", "city_locode": "KWE", "city": "Guigang", "city_slug": "guigang", "height_architecture_formatted": 99.6, "height_architecture_ft_formatted": "327", "floors_above": 31, "completed": 2016, "start": 2014, "structural_material": "", "functions": "residential", "retrofit_functions": "", "image": ""}, {"id": 31968, "url": "/building/tian-yue-shangcheng-10/31968", "name": "Tian Yue Shangcheng 10#", "status": "COM", "height_architecture": 99.6, "longitude": 0, "latitude": 0, "rank": 79, "name_linked": "<a href='/building/tian-yue-shangcheng-10/31968' target='_blank'>Tian Yue Shangcheng 10#</a>", "country_id": 34, "country_chinese": "", "city_id": 2821, "country_locode": "CN", "country_slug": "china", "city_locode": "KWE", "city": "Guigang", "city_slug": "guigang", "height_architecture_formatted": 99.6, "height_architecture_ft_formatted": "327", "floors_above": 30, "completed": 2016, "start": 2014, "structural_material": "", "functions": "residential", "retrofit_functions": "", "image": ""}, {"id": 31972, "url": "/building/tian-yue-shangcheng-15/31972", "name": "Tian Yue Shangcheng 15#", "status": "COM", "height_architecture": 99.6, "longitude": 0, "latitude": 0, "rank": 79, "name_linked": "<a href='/building/tian-yue-shangcheng-15/31972' target='_blank'>Tian Yue Shangcheng 15#</a>", "country_id": 34, "country_chinese": "", "city_id": 2821, "country_locode": "CN", "country_slug": "china", "city_locode": "KWE", "city": "Guigang", "city_slug": "guigang", "height_architecture_formatted": 99.6, "height_architecture_ft_formatted": "327", "floors_above": 30, "completed": 2016, "start": 2014, "structural_material": "", "functions": "residential", "retrofit_functions": "", "image": ""}, {"id": 32770, "url": "/building/guowang-garden-1/32770", "name": "Guowang Garden 1#", "status": "COM", "height_architecture": 99.2, "longitude": 0, "latitude": 0, "rank": 81, "name_linked": "<a href='/building/guowang-garden-1/32770' target='_blank'>Guowang Garden 1#</a>", "country_id": 34, "country_chinese": "", "city_id": 2821, "country_locode": "CN", "country_slug": "china", "city_locode": "KWE", "city": "Guigang", "city_slug": "guigang", "height_architecture_formatted": 99.2, "height_architecture_ft_formatted": "325", "floors_above": 32, "completed": 2015, "start": 2012, "structural_material": "", "functions": "residential", "retrofit_functions": "", "image": ""}, {"id": 32771, "url": "/building/guowang-garden-2/32771", "name": "Guowang Garden 2# ", "status": "COM", "height_architecture": 99.2, "longitude": 0, "latitude": 0, "rank": 81, "name_linked": "<a href='/building/guowang-garden-2/32771' target='_blank'>Guowang Garden 2# </a>", "country_id": 34, "country_chinese": "", "city_id": 2821, "country_locode": "CN", "country_slug": "china", "city_locode": "KWE", "city": "Guigang", "city_slug": "guigang", "height_architecture_formatted": 99.2, "height_architecture_ft_formatted": "325", "floors_above": 32, "completed": 2015, "start": 2012, "structural_material": "", "functions": "residential", "retrofit_functions": "", "image": ""}, {"id": 32772, "url": "/building/guowang-garden-3/32772", "name": "Guowang Garden 3# ", "status": "COM", "height_architecture": 99.2, "longitude": 0, "latitude": 0, "rank": 81, "name_linked": "<a href='/building/guowang-garden-3/32772' target='_blank'>Guowang Garden 3# </a>", "country_id": 34, "country_chinese": "", "city_id": 2821, "country_locode": "CN", "country_slug": "china", "city_locode": "KWE", "city": "Guigang", "city_slug": "guigang", "height_architecture_formatted": 99.2, "height_architecture_ft_formatted": "325", "floors_above": 32, "completed": 2015, "start": 2012, "structural_material": "", "functions": "residential", "retrofit_functions": "", "image": ""}, {"id": 32773, "url": "/building/guowang-garden-4/32773", "name": "Guowang Garden 4# ", "status": "COM", "height_architecture": 99.2, "longitude": 0, "latitude": 0, "rank": 81, "name_linked": "<a href='/building/guowang-garden-4/32773' target='_blank'>Guowang Garden 4# </a>", "country_id": 34, "country_chinese": "", "city_id": 2821, "country_locode": "CN", "country_slug": "china", "city_locode": "KWE", "city": "Guigang", "city_slug": "guigang", "height_architecture_formatted": 99.2, "height_architecture_ft_formatted": "325", "floors_above": 32, "completed": 2015, "start": 2012, "structural_material": "", "functions": "residential", "retrofit_functions": "", "image": ""}, {"id": 32774, "url": "/building/guowang-garden-5/32774", "name": "Guowang Garden 5# ", "status": "COM", "height_architecture": 99.2, "longitude": 0, "latitude": 0, "rank": 81, "name_linked": "<a href='/building/guowang-garden-5/32774' target='_blank'>Guowang Garden 5# </a>", "country_id": 34, "country_chinese": "", "city_id": 2821, "country_locode": "CN", "country_slug": "china", "city_locode": "KWE", "city": "Guigang", "city_slug": "guigang", "height_architecture_formatted": 99.2, "height_architecture_ft_formatted": "325", "floors_above": 32, "completed": 2015, "start": 2012, "structural_material": "", "functions": "residential", "retrofit_functions": "", "image": ""}, {"id": 32775, "url": "/building/guowang-garden-6/32775", "name": "Guowang Garden 6# ", "status": "COM", "height_architecture": 99.2, "longitude": 0, "latitude": 0, "rank": 81, "name_linked": "<a href='/building/guowang-garden-6/32775' target='_blank'>Guowang Garden 6# </a>", "country_id": 34, "country_chinese": "", "city_id": 2821, "country_locode": "CN", "country_slug": "china", "city_locode": "KWE", "city": "Guigang", "city_slug": "guigang", "height_architecture_formatted": 99.2, "height_architecture_ft_formatted": "325", "floors_above": 32, "completed": 2015, "start": 2012, "structural_material": "", "functions": "residential", "retrofit_functions": "", "image": ""}, {"id": 32851, "url": "/building/oriental-paris-1/32851", "name": "Oriental Paris 1#", "status": "COM", "height_architecture": 99.2, "longitude": 0, "latitude": 0, "rank": 81, "name_linked": "<a href='/building/oriental-paris-1/32851' target='_blank'>Oriental Paris 1#</a>", "country_id": 34, "country_chinese": "", "city_id": 2821, "country_locode": "CN", "country_slug": "china", "city_locode": "KWE", "city": "Guigang", "city_slug": "guigang", "height_architecture_formatted": 99.2, "height_architecture_ft_formatted": "325", "floors_above": 32, "completed": 2011, "start": 2009, "structural_material": "", "functions": "residential", "retrofit_functions": "", "image": ""}, {"id": 32852, "url": "/building/oriental-paris-2/32852", "name": "Oriental Paris 2#", "status": "COM", "height_architecture": 99.2, "longitude": 0, "latitude": 0, "rank": 81, "name_linked": "<a href='/building/oriental-paris-2/32852' target='_blank'>Oriental Paris 2#</a>", "country_id": 34, "country_chinese": "", "city_id": 2821, "country_locode": "CN", "country_slug": "china", "city_locode": "KWE", "city": "Guigang", "city_slug": "guigang", "height_architecture_formatted": 99.2, "height_architecture_ft_formatted": "325", "floors_above": 32, "completed": 2011, "start": 2009, "structural_material": "", "functions": "residential", "retrofit_functions": "", "image": ""}, {"id": 32853, "url": "/building/oriental-paris-3/32853", "name": "Oriental Paris 3#", "status": "COM", "height_architecture": 99.2, "longitude": 0, "latitude": 0, "rank": 81, "name_linked": "<a href='/building/oriental-paris-3/32853' target='_blank'>Oriental Paris 3#</a>", "country_id": 34, "country_chinese": "", "city_id": 2821, "country_locode": "CN", "country_slug": "china", "city_locode": "KWE", "city": "Guigang", "city_slug": "guigang", "height_architecture_formatted": 99.2, "height_architecture_ft_formatted": "325", "floors_above": 32, "completed": 2011, "start": 2009, "structural_material": "", "functions": "residential", "retrofit_functions": "", "image": ""}, {"id": 32854, "url": "/building/oriental-paris-4/32854", "name": "Oriental Paris 4#", "status": "COM", "height_architecture": 99.2, "longitude": 0, "latitude": 0, "rank": 81, "name_linked": "<a href='/building/oriental-paris-4/32854' target='_blank'>Oriental Paris 4#</a>", "country_id": 34, "country_chinese": "", "city_id": 2821, "country_locode": "CN", "country_slug": "china", "city_locode": "KWE", "city": "Guigang", "city_slug": "guigang", "height_architecture_formatted": 99.2, "height_architecture_ft_formatted": "325", "floors_above": 32, "completed": 2011, "start": 2009, "structural_material": "", "functions": "residential", "retrofit_functions": "", "image": ""}, {"id": 32850, "url": "/building/oriental-paris-5/32850", "name": "Oriental Paris 5#", "status": "COM", "height_architecture": 99.2, "longitude": 0, "latitude": 0, "rank": 81, "name_linked": "<a href='/building/oriental-paris-5/32850' target='_blank'>Oriental Paris 5#</a>", "country_id": 34, "country_chinese": "", "city_id": 2821, "country_locode": "CN", "country_slug": "china", "city_locode": "KWE", "city": "Guigang", "city_slug": "guigang", "height_architecture_formatted": 99.2, "height_architecture_ft_formatted": "325", "floors_above": 32, "completed": 2011, "start": 2009, "structural_material": "", "functions": "residential", "retrofit_functions": "", "image": ""}, {"id": 32553, "url": "/building/elysee-wutai-9/32553", "name": "Elysee Wutai 9#", "status": "UC", "height_architecture": 99.2, "longitude": 0, "latitude": 0, "rank": 92, "name_linked": "<a href='/building/elysee-wutai-9/32553' target='_blank'>Elysee Wutai 9#</a>", "country_id": 34, "country_chinese": "", "city_id": 2821, "country_locode": "CN", "country_slug": "china", "city_locode": "KWE", "city": "Guigang", "city_slug": "guigang", "height_architecture_formatted": 99.2, "height_architecture_ft_formatted": "325", "floors_above": 31, "completed": 2019, "start": 2017, "structural_material": "", "functions": "residential", "retrofit_functions": "", "image": ""}, {"id": 32545, "url": "/building/elysee-wutai-10/32545", "name": "Elysee Wutai 10#", "status": "UC", "height_architecture": 99.2, "longitude": 0, "latitude": 0, "rank": 93, "name_linked": "<a href='/building/elysee-wutai-10/32545' target='_blank'>Elysee Wutai 10#</a>", "country_id": 34, "country_chinese": "", "city_id": 2821, "country_locode": "CN", "country_slug": "china", "city_locode": "KWE", "city": "Guigang", "city_slug": "guigang", "height_architecture_formatted": 99.2, "height_architecture_ft_formatted": "325", "floors_above": 30, "completed": 2019, "start": 2017, "structural_material": "", "functions": "residential", "retrofit_functions": "", "image": ""}, {"id": 32460, "url": "/building/sheng-jia-jiayuan-1/32460", "name": "Sheng Jia Jiayuan 1#", "status": "UC", "height_architecture": 98.9, "longitude": 0, "latitude": 0, "rank": 94, "name_linked": "<a href='/building/sheng-jia-jiayuan-1/32460' target='_blank'>Sheng Jia Jiayuan 1#</a>", "country_id": 34, "country_chinese": "", "city_id": 2821, "country_locode": "CN", "country_slug": "china", "city_locode": "KWE", "city": "Guigang", "city_slug": "guigang", "height_architecture_formatted": 98.9, "height_architecture_ft_formatted": "324", "floors_above": 32, "completed": 2019, "start": 2017, "structural_material": "concrete", "functions": "residential", "retrofit_functions": "", "image": ""}, {"id": 32461, "url": "/building/sheng-jia-jiayuan-2/32461", "name": "Sheng Jia Jiayuan 2#", "status": "UC", "height_architecture": 98.9, "longitude": 0, "latitude": 0, "rank": 94, "name_linked": "<a href='/building/sheng-jia-jiayuan-2/32461' target='_blank'>Sheng Jia Jiayuan 2#</a>", "country_id": 34, "country_chinese": "", "city_id": 2821, "country_locode": "CN", "country_slug": "china", "city_locode": "KWE", "city": "Guigang", "city_slug": "guigang", "height_architecture_formatted": 98.9, "height_architecture_ft_formatted": "324", "floors_above": 32, "completed": 2019, "start": 2017, "structural_material": "concrete", "functions": "residential", "retrofit_functions": "", "image": ""}, {"id": 32462, "url": "/building/sheng-jia-jiayuan-3/32462", "name": "Sheng Jia Jiayuan 3#", "status": "UC", "height_architecture": 98.9, "longitude": 0, "latitude": 0, "rank": 94, "name_linked": "<a href='/building/sheng-jia-jiayuan-3/32462' target='_blank'>Sheng Jia Jiayuan 3#</a>", "country_id": 34, "country_chinese": "", "city_id": 2821, "country_locode": "CN", "country_slug": "china", "city_locode": "KWE", "city": "Guigang", "city_slug": "guigang", "height_architecture_formatted": 98.9, "height_architecture_ft_formatted": "324", "floors_above": 32, "completed": 2019, "start": 2017, "structural_material": "concrete", "functions": "residential", "retrofit_functions": "", "image": ""}, {"id": 32463, "url": "/building/sheng-jia-jiayuan-4/32463", "name": "Sheng Jia Jiayuan 4#", "status": "UC", "height_architecture": 98.9, "longitude": 0, "latitude": 0, "rank": 94, "name_linked": "<a href='/building/sheng-jia-jiayuan-4/32463' target='_blank'>Sheng Jia Jiayuan 4#</a>", "country_id": 34, "country_chinese": "", "city_id": 2821, "country_locode": "CN", "country_slug": "china", "city_locode": "KWE", "city": "Guigang", "city_slug": "guigang", "height_architecture_formatted": 98.9, "height_architecture_ft_formatted": "324", "floors_above": 32, "completed": 2019, "start": 2017, "structural_material": "concrete", "functions": "residential", "retrofit_functions": "", "image": ""}, {"id": 32464, "url": "/building/sheng-jia-jiayuan-5/32464", "name": "Sheng Jia Jiayuan 5#", "status": "UC", "height_architecture": 98.9, "longitude": 0, "latitude": 0, "rank": 94, "name_linked": "<a href='/building/sheng-jia-jiayuan-5/32464' target='_blank'>Sheng Jia Jiayuan 5#</a>", "country_id": 34, "country_chinese": "", "city_id": 2821, "country_locode": "CN", "country_slug": "china", "city_locode": "KWE", "city": "Guigang", "city_slug": "guigang", "height_architecture_formatted": 98.9, "height_architecture_ft_formatted": "324", "floors_above": 32, "completed": 2019, "start": 2017, "structural_material": "concrete", "functions": "residential", "retrofit_functions": "", "image": ""}, {"id": 32465, "url": "/building/sheng-jia-jiayuan-6/32465", "name": "Sheng Jia Jiayuan 6#", "status": "UC", "height_architecture": 98.9, "longitude": 0, "latitude": 0, "rank": 94, "name_linked": "<a href='/building/sheng-jia-jiayuan-6/32465' target='_blank'>Sheng Jia Jiayuan 6#</a>", "country_id": 34, "country_chinese": "", "city_id": 2821, "country_locode": "CN", "country_slug": "china", "city_locode": "KWE", "city": "Guigang", "city_slug": "guigang", "height_architecture_formatted": 98.9, "height_architecture_ft_formatted": "324", "floors_above": 32, "completed": 2019, "start": 2017, "structural_material": "concrete", "functions": "residential", "retrofit_functions": "", "image": ""}, {"id": 32466, "url": "/building/sheng-jia-jiayuan-7/32466", "name": "Sheng Jia Jiayuan 7#", "status": "UC", "height_architecture": 98.9, "longitude": 0, "latitude": 0, "rank": 94, "name_linked": "<a href='/building/sheng-jia-jiayuan-7/32466' target='_blank'>Sheng Jia Jiayuan 7#</a>", "country_id": 34, "country_chinese": "", "city_id": 2821, "country_locode": "CN", "country_slug": "china", "city_locode": "KWE", "city": "Guigang", "city_slug": "guigang", "height_architecture_formatted": 98.9, "height_architecture_ft_formatted": "324", "floors_above": 32, "completed": 2019, "start": 2017, "structural_material": "concrete", "functions": "residential", "retrofit_functions": "", "image": ""}, {"id": 32826, "url": "/building/xijiang-greentown-5/32826", "name": "Xijiang Greentown 5#", "status": "UCT", "height_architecture": 98.6, "longitude": 0, "latitude": 0, "rank": 101, "name_linked": "<a href='/building/xijiang-greentown-5/32826' target='_blank'>Xijiang Greentown 5#</a>", "country_id": 34, "country_chinese": "", "city_id": 2821, "country_locode": "CN", "country_slug": "china", "city_locode": "KWE", "city": "Guigang", "city_slug": "guigang", "height_architecture_formatted": 98.6, "height_architecture_ft_formatted": "323", "floors_above": 30, "completed": 2018, "start": 2017, "structural_material": "", "functions": "residential", "retrofit_functions": "", "image": ""}, {"id": 32828, "url": "/building/xijiang-greentown-7/32828", "name": "Xijiang Greentown 7#", "status": "UCT", "height_architecture": 98.6, "longitude": 0, "latitude": 0, "rank": 101, "name_linked": "<a href='/building/xijiang-greentown-7/32828' target='_blank'>Xijiang Greentown 7#</a>", "country_id": 34, "country_chinese": "", "city_id": 2821, "country_locode": "CN", "country_slug": "china", "city_locode": "KWE", "city": "Guigang", "city_slug": "guigang", "height_architecture_formatted": 98.6, "height_architecture_ft_formatted": "323", "floors_above": 30, "completed": 2018, "start": 2017, "structural_material": "", "functions": "residential", "retrofit_functions": "", "image": ""}, {"id": 32829, "url": "/building/xijiang-greentown-8/32829", "name": "Xijiang Greentown 8#", "status": "UCT", "height_architecture": 98.6, "longitude": 0, "latitude": 0, "rank": 101, "name_linked": "<a href='/building/xijiang-greentown-8/32829' target='_blank'>Xijiang Greentown 8#</a>", "country_id": 34, "country_chinese": "", "city_id": 2821, "country_locode": "CN", "country_slug": "china", "city_locode": "KWE", "city": "Guigang", "city_slug": "guigang", "height_architecture_formatted": 98.6, "height_architecture_ft_formatted": "323", "floors_above": 30, "completed": 2018, "start": 2017, "structural_material": "", "functions": "residential", "retrofit_functions": "", "image": ""}, {"id": 32706, "url": "/building/chinatown/32706", "name": "Chinatown", "status": "COM", "height_architecture": 98.6, "longitude": 0, "latitude": 0, "rank": 104, "name_linked": "<a href='/building/chinatown/32706' target='_blank'>Chinatown</a>", "country_id": 34, "country_chinese": "", "city_id": 2821, "country_locode": "CN", "country_slug": "china", "city_locode": "KWE", "city": "Guigang", "city_slug": "guigang", "height_architecture_formatted": 98.6, "height_architecture_ft_formatted": "323", "floors_above": 28, "completed": 2013, "start": 2010, "structural_material": "", "functions": "office / hotel / retail", "retrofit_functions": "", "image": ""}, {"id": 32544, "url": "/building/elysee-wutai-1/32544", "name": "Elysee Wutai 1#", "status": "COM", "height_architecture": 98.2, "longitude": 0, "latitude": 0, "rank": 105, "name_linked": "<a href='/building/elysee-wutai-1/32544' target='_blank'>Elysee Wutai 1#</a>", "country_id": 34, "country_chinese": "", "city_id": 2821, "country_locode": "CN", "country_slug": "china", "city_locode": "KWE", "city": "Guigang", "city_slug": "guigang", "height_architecture_formatted": 98.2, "height_architecture_ft_formatted": "322", "floors_above": 31, "completed": 2018, "start": 2016, "structural_material": "", "functions": "residential", "retrofit_functions": "", "image": ""}, {"id": 32546, "url": "/building/elysee-wutai-2/32546", "name": "Elysee Wutai 2#", "status": "COM", "height_architecture": 98.2, "longitude": 0, "latitude": 0, "rank": 105, "name_linked": "<a href='/building/elysee-wutai-2/32546' target='_blank'>Elysee Wutai 2#</a>", "country_id": 34, "country_chinese": "", "city_id": 2821, "country_locode": "CN", "country_slug": "china", "city_locode": "KWE", "city": "Guigang", "city_slug": "guigang", "height_architecture_formatted": 98.2, "height_architecture_ft_formatted": "322", "floors_above": 31, "completed": 2018, "start": 2016, "structural_material": "", "functions": "residential", "retrofit_functions": "", "image": ""}, {"id": 32300, "url": "/building/guanghui-east-lake-city-4/32300", "name": "Guanghui East Lake City 4#", "status": "COM", "height_architecture": 98, "longitude": 0, "latitude": 0, "rank": 107, "name_linked": "<a href='/building/guanghui-east-lake-city-4/32300' target='_blank'>Guanghui East Lake City 4#</a>", "country_id": 34, "country_chinese": "", "city_id": 2821, "country_locode": "CN", "country_slug": "china", "city_locode": "KWE", "city": "Guigang", "city_slug": "guigang", "height_architecture_formatted": 98, "height_architecture_ft_formatted": "322", "floors_above": 33, "completed": 2014, "start": 2012, "structural_material": "", "functions": "residential", "retrofit_functions": "", "image": ""}, {"id": 32302, "url": "/building/guanghui-east-lake-city-6/32302", "name": "Guanghui East Lake City 6#", "status": "COM", "height_architecture": 98, "longitude": 0, "latitude": 0, "rank": 107, "name_linked": "<a href='/building/guanghui-east-lake-city-6/32302' target='_blank'>Guanghui East Lake City 6#</a>", "country_id": 34, "country_chinese": "", "city_id": 2821, "country_locode": "CN", "country_slug": "china", "city_locode": "KWE", "city": "Guigang", "city_slug": "guigang", "height_architecture_formatted": 98, "height_architecture_ft_formatted": "322", "floors_above": 33, "completed": 2014, "start": 2012, "structural_material": "", "functions": "residential", "retrofit_functions": "", "image": ""}, {"id": 32572, "url": "/building/guigang-donghu-10/32572", "name": "Guigang Donghu 10#", "status": "COM", "height_architecture": 97.95, "longitude": 0, "latitude": 0, "rank": 109, "name_linked": "<a href='/building/guigang-donghu-10/32572' target='_blank'>Guigang Donghu 10#</a>", "country_id": 34, "country_chinese": "", "city_id": 2821, "country_locode": "CN", "country_slug": "china", "city_locode": "KWE", "city": "Guigang", "city_slug": "guigang", "height_architecture_formatted": 98, "height_architecture_ft_formatted": "321", "floors_above": 33, "completed": 2015, "start": 2014, "structural_material": "", "functions": "residential", "retrofit_functions": "", "image": ""}, {"id": 32569, "url": "/building/guigang-donghu-16/32569", "name": "Guigang Donghu 16#", "status": "COM", "height_architecture": 97.95, "longitude": 0, "latitude": 0, "rank": 109, "name_linked": "<a href='/building/guigang-donghu-16/32569' target='_blank'>Guigang Donghu 16#</a>", "country_id": 34, "country_chinese": "", "city_id": 2821, "country_locode": "CN", "country_slug": "china", "city_locode": "KWE", "city": "Guigang", "city_slug": "guigang", "height_architecture_formatted": 98, "height_architecture_ft_formatted": "321", "floors_above": 33, "completed": 2015, "start": 2014, "structural_material": "", "functions": "residential", "retrofit_functions": "", "image": ""}, {"id": 32816, "url": "/building/guigang-donghu-23/32816", "name": "Guigang Donghu 23#", "status": "COM", "height_architecture": 97.95, "longitude": 0, "latitude": 0, "rank": 109, "name_linked": "<a href='/building/guigang-donghu-23/32816' target='_blank'>Guigang Donghu 23#</a>", "country_id": 34, "country_chinese": "", "city_id": 2821, "country_locode": "CN", "country_slug": "china", "city_locode": "KWE", "city": "Guigang", "city_slug": "guigang", "height_architecture_formatted": 98, "height_architecture_ft_formatted": "321", "floors_above": 33, "completed": 2021, "start": 2019, "structural_material": "", "functions": "residential", "retrofit_functions": "", "image": ""}, {"id": 32568, "url": "/building/guigang-donghu-7/32568", "name": "Guigang Donghu 7#", "status": "COM", "height_architecture": 97.95, "longitude": 0, "latitude": 0, "rank": 109, "name_linked": "<a href='/building/guigang-donghu-7/32568' target='_blank'>Guigang Donghu 7#</a>", "country_id": 34, "country_chinese": "", "city_id": 2821, "country_locode": "CN", "country_slug": "china", "city_locode": "KWE", "city": "Guigang", "city_slug": "guigang", "height_architecture_formatted": 98, "height_architecture_ft_formatted": "321", "floors_above": 33, "completed": 2015, "start": 2014, "structural_material": "", "functions": "residential", "retrofit_functions": "", "image": ""}, {"id": 32570, "url": "/building/guigang-donghu-8/32570", "name": "Guigang Donghu 8#", "status": "COM", "height_architecture": 97.95, "longitude": 0, "latitude": 0, "rank": 109, "name_linked": "<a href='/building/guigang-donghu-8/32570' target='_blank'>Guigang Donghu 8#</a>", "country_id": 34, "country_chinese": "", "city_id": 2821, "country_locode": "CN", "country_slug": "china", "city_locode": "KWE", "city": "Guigang", "city_slug": "guigang", "height_architecture_formatted": 98, "height_architecture_ft_formatted": "321", "floors_above": 33, "completed": 2015, "start": 2014, "structural_material": "", "functions": "residential", "retrofit_functions": "", "image": ""}, {"id": 32571, "url": "/building/guigang-donghu-9/32571", "name": "Guigang Donghu 9#", "status": "COM", "height_architecture": 97.95, "longitude": 0, "latitude": 0, "rank": 109, "name_linked": "<a href='/building/guigang-donghu-9/32571' target='_blank'>Guigang Donghu 9#</a>", "country_id": 34, "country_chinese": "", "city_id": 2821, "country_locode": "CN", "country_slug": "china", "city_locode": "KWE", "city": "Guigang", "city_slug": "guigang", "height_architecture_formatted": 98, "height_architecture_ft_formatted": "321", "floors_above": 33, "completed": 2015, "start": 2014, "structural_material": "", "functions": "residential", "retrofit_functions": "", "image": ""}, {"id": 32738, "url": "/building/golden-age-dutch-city-a-1-area-3/32738", "name": "Golden Age Dutch City A-1 Area #3", "status": "COM", "height_architecture": 97.7, "longitude": 0, "latitude": 0, "rank": 115, "name_linked": "<a href='/building/golden-age-dutch-city-a-1-area-3/32738' target='_blank'>Golden Age Dutch City A-1 Area #3</a>", "country_id": 34, "country_chinese": "", "city_id": 2821, "country_locode": "CN", "country_slug": "china", "city_locode": "KWE", "city": "Guigang", "city_slug": "guigang", "height_architecture_formatted": 97.7, "height_architecture_ft_formatted": "321", "floors_above": 32, "completed": 2018, "start": 2016, "structural_material": "", "functions": "residential", "retrofit_functions": "", "image": ""}, {"id": 32741, "url": "/building/golden-age-dutch-city-a-1-area-7/32741", "name": "Golden Age Dutch City A-1 Area #7", "status": "COM", "height_architecture": 97.7, "longitude": 0, "latitude": 0, "rank": 115, "name_linked": "<a href='/building/golden-age-dutch-city-a-1-area-7/32741' target='_blank'>Golden Age Dutch City A-1 Area #7</a>", "country_id": 34, "country_chinese": "", "city_id": 2821, "country_locode": "CN", "country_slug": "china", "city_locode": "KWE", "city": "Guigang", "city_slug": "guigang", "height_architecture_formatted": 97.7, "height_architecture_ft_formatted": "321", "floors_above": 32, "completed": 2018, "start": 2016, "structural_material": "", "functions": "residential", "retrofit_functions": "", "image": ""}, {"id": 32297, "url": "/building/guanghui-east-lake-city-1/32297", "name": "Guanghui East Lake City 1#", "status": "COM", "height_architecture": 97.4, "longitude": 0, "latitude": 0, "rank": 117, "name_linked": "<a href='/building/guanghui-east-lake-city-1/32297' target='_blank'>Guanghui East Lake City 1#</a>", "country_id": 34, "country_chinese": "", "city_id": 2821, "country_locode": "CN", "country_slug": "china", "city_locode": "KWE", "city": "Guigang", "city_slug": "guigang", "height_architecture_formatted": 97.4, "height_architecture_ft_formatted": "320", "floors_above": 33, "completed": 2014, "start": 2012, "structural_material": "", "functions": "residential", "retrofit_functions": "", "image": ""}, {"id": 32298, "url": "/building/guanghui-east-lake-city-2/32298", "name": "Guanghui East Lake City 2# ", "status": "COM", "height_architecture": 97.4, "longitude": 0, "latitude": 0, "rank": 117, "name_linked": "<a href='/building/guanghui-east-lake-city-2/32298' target='_blank'>Guanghui East Lake City 2# </a>", "country_id": 34, "country_chinese": "", "city_id": 2821, "country_locode": "CN", "country_slug": "china", "city_locode": "KWE", "city": "Guigang", "city_slug": "guigang", "height_architecture_formatted": 97.4, "height_architecture_ft_formatted": "320", "floors_above": 33, "completed": 2014, "start": 2012, "structural_material": "", "functions": "residential", "retrofit_functions": "", "image": ""}, {"id": 32299, "url": "/building/guanghui-east-lake-city-3/32299", "name": "Guanghui East Lake City 3# ", "status": "COM", "height_architecture": 97.4, "longitude": 0, "latitude": 0, "rank": 117, "name_linked": "<a href='/building/guanghui-east-lake-city-3/32299' target='_blank'>Guanghui East Lake City 3# </a>", "country_id": 34, "country_chinese": "", "city_id": 2821, "country_locode": "CN", "country_slug": "china", "city_locode": "KWE", "city": "Guigang", "city_slug": "guigang", "height_architecture_formatted": 97.4, "height_architecture_ft_formatted": "320", "floors_above": 33, "completed": 2014, "start": 2012, "structural_material": "", "functions": "residential", "retrofit_functions": "", "image": ""}, {"id": 32296, "url": "/building/guanghui-east-lake-city-9/32296", "name": "Guanghui East Lake City 9#", "status": "COM", "height_architecture": 97.4, "longitude": 0, "latitude": 0, "rank": 117, "name_linked": "<a href='/building/guanghui-east-lake-city-9/32296' target='_blank'>Guanghui East Lake City 9#</a>", "country_id": 34, "country_chinese": "", "city_id": 2821, "country_locode": "CN", "country_slug": "china", "city_locode": "KWE", "city": "Guigang", "city_slug": "guigang", "height_architecture_formatted": 97.4, "height_architecture_ft_formatted": "320", "floors_above": 33, "completed": 2015, "start": 2013, "structural_material": "", "functions": "residential", "retrofit_functions": "", "image": ""}, {"id": 31961, "url": "/building/tian-yue-shangcheng-2/31961", "name": "Tian Yue Shangcheng 2#", "status": "COM", "height_architecture": 93.9, "longitude": 0, "latitude": 0, "rank": 121, "name_linked": "<a href='/building/tian-yue-shangcheng-2/31961' target='_blank'>Tian Yue Shangcheng 2#</a>", "country_id": 34, "country_chinese": "", "city_id": 2821, "country_locode": "CN", "country_slug": "china", "city_locode": "KWE", "city": "Guigang", "city_slug": "guigang", "height_architecture_formatted": 93.9, "height_architecture_ft_formatted": "308", "floors_above": 28, "completed": 2014, "start": "-", "structural_material": "", "functions": "residential", "retrofit_functions": "", "image": ""}, {"id": 32549, "url": "/building/elysee-wutai-5/32549", "name": "Elysee Wutai 5#", "status": "UCT", "height_architecture": 90.8, "longitude": 0, "latitude": 0, "rank": 122, "name_linked": "<a href='/building/elysee-wutai-5/32549' target='_blank'>Elysee Wutai 5#</a>", "country_id": 34, "country_chinese": "", "city_id": 2821, "country_locode": "CN", "country_slug": "china", "city_locode": "KWE", "city": "Guigang", "city_slug": "guigang", "height_architecture_formatted": 90.8, "height_architecture_ft_formatted": "298", "floors_above": 29, "completed": 2018, "start": 2016, "structural_material": "", "functions": "residential", "retrofit_functions": "", "image": ""}, {"id": 32547, "url": "/building/elysee-wutai-3/32547", "name": "Elysee Wutai 3#", "status": "COM", "height_architecture": 89.2, "longitude": 0, "latitude": 0, "rank": 123, "name_linked": "<a href='/building/elysee-wutai-3/32547' target='_blank'>Elysee Wutai 3#</a>", "country_id": 34, "country_chinese": "", "city_id": 2821, "country_locode": "CN", "country_slug": "china", "city_locode": "KWE", "city": "Guigang", "city_slug": "guigang", "height_architecture_formatted": 89.2, "height_architecture_ft_formatted": "293", "floors_above": 28, "completed": 2018, "start": 2016, "structural_material": "", "functions": "residential", "retrofit_functions": "", "image": ""}, {"id": 31959, "url": "/building/tian-yue-shangcheng-16/31959", "name": "Tian Yue Shangcheng 16#", "status": "COM", "height_architecture": 88, "longitude": 0, "latitude": 0, "rank": 124, "name_linked": "<a href='/building/tian-yue-shangcheng-16/31959' target='_blank'>Tian Yue Shangcheng 16#</a>", "country_id": 34, "country_chinese": "", "city_id": 2821, "country_locode": "CN", "country_slug": "china", "city_locode": "KWE", "city": "Guigang", "city_slug": "guigang", "height_architecture_formatted": 88, "height_architecture_ft_formatted": "289", "floors_above": 26, "completed": 2016, "start": 2014, "structural_material": "", "functions": "office", "retrofit_functions": "", "image": ""}, {"id": 32573, "url": "/building/guigang-donghu-11/32573", "name": "Guigang Donghu 11#", "status": "COM", "height_architecture": 87.95, "longitude": 0, "latitude": 0, "rank": 125, "name_linked": "<a href='/building/guigang-donghu-11/32573' target='_blank'>Guigang Donghu 11#</a>", "country_id": 34, "country_chinese": "", "city_id": 2821, "country_locode": "CN", "country_slug": "china", "city_locode": "KWE", "city": "Guigang", "city_slug": "guigang", "height_architecture_formatted": 88, "height_architecture_ft_formatted": "289", "floors_above": 26, "completed": 2015, "start": 2014, "structural_material": "", "functions": "residential", "retrofit_functions": "", "image": ""}, {"id": 32574, "url": "/building/guigang-donghu-12/32574", "name": "Guigang Donghu 12#", "status": "COM", "height_architecture": 87.95, "longitude": 0, "latitude": 0, "rank": 125, "name_linked": "<a href='/building/guigang-donghu-12/32574' target='_blank'>Guigang Donghu 12#</a>", "country_id": 34, "country_chinese": "", "city_id": 2821, "country_locode": "CN", "country_slug": "china", "city_locode": "KWE", "city": "Guigang", "city_slug": "guigang", "height_architecture_formatted": 88, "height_architecture_ft_formatted": "289", "floors_above": 26, "completed": 2015, "start": 2014, "structural_material": "", "functions": "residential", "retrofit_functions": "", "image": ""}, {"id": 32807, "url": "/building/guigang-donghu-19/32807", "name": "Guigang Donghu 19#", "status": "UC", "height_architecture": 87.75, "longitude": 0, "latitude": 0, "rank": 127, "name_linked": "<a href='/building/guigang-donghu-19/32807' target='_blank'>Guigang Donghu 19#</a>", "country_id": 34, "country_chinese": "", "city_id": 2821, "country_locode": "CN", "country_slug": "china", "city_locode": "KWE", "city": "Guigang", "city_slug": "guigang", "height_architecture_formatted": 87.8, "height_architecture_ft_formatted": "288", "floors_above": 18, "completed": 2019, "start": 2017, "structural_material": "", "functions": "office", "retrofit_functions": "", "image": ""}, {"id": 32808, "url": "/building/guigang-donghu-20/32808", "name": "Guigang Donghu 20#", "status": "UC", "height_architecture": 87.75, "longitude": 0, "latitude": 0, "rank": 127, "name_linked": "<a href='/building/guigang-donghu-20/32808' target='_blank'>Guigang Donghu 20#</a>", "country_id": 34, "country_chinese": "", "city_id": 2821, "country_locode": "CN", "country_slug": "china", "city_locode": "KWE", "city": "Guigang", "city_slug": "guigang", "height_architecture_formatted": 87.8, "height_architecture_ft_formatted": "288", "floors_above": 18, "completed": 2019, "start": 2017, "structural_material": "", "functions": "office", "retrofit_functions": "", "image": ""}, {"id": 32691, "url": "/building/qili-xiangjiang-a/32691", "name": "Qili Xiangjiang A", "status": "COM", "height_architecture": 83.2, "longitude": 0, "latitude": 0, "rank": 129, "name_linked": "<a href='/building/qili-xiangjiang-a/32691' target='_blank'>Qili Xiangjiang A</a>", "country_id": 34, "country_chinese": "", "city_id": 2821, "country_locode": "CN", "country_slug": "china", "city_locode": "KWE", "city": "Guigang", "city_slug": "guigang", "height_architecture_formatted": 83.2, "height_architecture_ft_formatted": "273", "floors_above": 26, "completed": 2013, "start": 2011, "structural_material": "", "functions": "residential", "retrofit_functions": "", "image": ""}, {"id": 32692, "url": "/building/qili-xiangjiang-b/32692", "name": "Qili Xiangjiang B", "status": "COM", "height_architecture": 83.2, "longitude": 0, "latitude": 0, "rank": 129, "name_linked": "<a href='/building/qili-xiangjiang-b/32692' target='_blank'>Qili Xiangjiang B</a>", "country_id": 34, "country_chinese": "", "city_id": 2821, "country_locode": "CN", "country_slug": "china", "city_locode": "KWE", "city": "Guigang", "city_slug": "guigang", "height_architecture_formatted": 83.2, "height_architecture_ft_formatted": "273", "floors_above": 26, "completed": 2013, "start": 2011, "structural_material": "", "functions": "residential", "retrofit_functions": "", "image": ""}, {"id": 33062, "url": "/building/guanghuiholy-lake-city-5/33062", "name": "Guanghui\u00b7Holy Lake City #5", "status": "COM", "height_architecture": 81.3, "longitude": 0, "latitude": 0, "rank": 131, "name_linked": "<a href='/building/guanghuiholy-lake-city-5/33062' target='_blank'>Guanghui\u00b7Holy Lake City #5</a>", "country_id": 34, "country_chinese": "", "city_id": 2821, "country_locode": "CN", "country_slug": "china", "city_locode": "GUG", "city": "Guigang", "city_slug": "guigang", "height_architecture_formatted": 81.3, "height_architecture_ft_formatted": "267", "floors_above": 26, "completed": 2014, "start": 2013, "structural_material": "", "functions": "residential", "retrofit_functions": "", "image": ""}, {"id": 33069, "url": "/building/guanghuiholy-lake-city-23/33069", "name": "Guanghui\u00b7Holy Lake City 23#", "status": "UC", "height_architecture": 81.3, "longitude": 0, "latitude": 0, "rank": 131, "name_linked": "<a href='/building/guanghuiholy-lake-city-23/33069' target='_blank'>Guanghui\u00b7Holy Lake City 23#</a>", "country_id": 34, "country_chinese": "", "city_id": 2821, "country_locode": "CN", "country_slug": "china", "city_locode": "GUG", "city": "Guigang", "city_slug": "guigang", "height_architecture_formatted": 81.3, "height_architecture_ft_formatted": "267", "floors_above": 26, "completed": 2019, "start": 2017, "structural_material": "", "functions": "residential", "retrofit_functions": "", "image": ""}, {"id": 33068, "url": "/building/guanghuiholy-lake-city-19/33068", "name": "Guanghui\u00b7Holy Lake City #19", "status": "UC", "height_architecture": 78.1, "longitude": 0, "latitude": 0, "rank": 133, "name_linked": "<a href='/building/guanghuiholy-lake-city-19/33068' target='_blank'>Guanghui\u00b7Holy Lake City #19</a>", "country_id": 34, "country_chinese": "", "city_id": 2821, "country_locode": "CN", "country_slug": "china", "city_locode": "GUG", "city": "Guigang", "city_slug": "guigang", "height_architecture_formatted": 78.1, "height_architecture_ft_formatted": "256", "floors_above": 25, "completed": 2019, "start": 2017, "structural_material": "", "functions": "residential", "retrofit_functions": "", "image": ""}, {"id": 32301, "url": "/building/guanghui-east-lake-city-5/32301", "name": "Guanghui East Lake City 5#", "status": "COM", "height_architecture": 77.7, "longitude": 0, "latitude": 0, "rank": 134, "name_linked": "<a href='/building/guanghui-east-lake-city-5/32301' target='_blank'>Guanghui East Lake City 5#</a>", "country_id": 34, "country_chinese": "", "city_id": 2821, "country_locode": "CN", "country_slug": "china", "city_locode": "KWE", "city": "Guigang", "city_slug": "guigang", "height_architecture_formatted": 77.7, "height_architecture_ft_formatted": "255", "floors_above": 26, "completed": 2015, "start": 2012, "structural_material": "", "functions": "residential", "retrofit_functions": "", "image": ""}, {"id": 32743, "url": "/building/golden-age-dutch-city-a-2-area-1/32743", "name": "Golden Age Dutch City A-2 Area #1", "status": "COM", "height_architecture": 75.9, "longitude": 0, "latitude": 0, "rank": 135, "name_linked": "<a href='/building/golden-age-dutch-city-a-2-area-1/32743' target='_blank'>Golden Age Dutch City A-2 Area #1</a>", "country_id": 34, "country_chinese": "", "city_id": 2821, "country_locode": "CN", "country_slug": "china", "city_locode": "KWE", "city": "Guigang", "city_slug": "guigang", "height_architecture_formatted": 75.9, "height_architecture_ft_formatted": "249", "floors_above": 24, "completed": 2016, "start": 2014, "structural_material": "", "functions": "residential", "retrofit_functions": "", "image": ""}, {"id": 32744, "url": "/building/golden-age-dutch-city-a-2-area-2/32744", "name": "Golden Age Dutch City A-2 Area #2", "status": "COM", "height_architecture": 75.9, "longitude": 0, "latitude": 0, "rank": 135, "name_linked": "<a href='/building/golden-age-dutch-city-a-2-area-2/32744' target='_blank'>Golden Age Dutch City A-2 Area #2</a>", "country_id": 34, "country_chinese": "", "city_id": 2821, "country_locode": "CN", "country_slug": "china", "city_locode": "KWE", "city": "Guigang", "city_slug": "guigang", "height_architecture_formatted": 75.9, "height_architecture_ft_formatted": "249", "floors_above": 24, "completed": 2016, "start": 2014, "structural_material": "", "functions": "residential", "retrofit_functions": "", "image": ""}, {"id": 32746, "url": "/building/golden-age-dutch-city-a-2-area-4/32746", "name": "Golden Age Dutch City A-2 Area #4", "status": "COM", "height_architecture": 75.9, "longitude": 0, "latitude": 0, "rank": 135, "name_linked": "<a href='/building/golden-age-dutch-city-a-2-area-4/32746' target='_blank'>Golden Age Dutch City A-2 Area #4</a>", "country_id": 34, "country_chinese": "", "city_id": 2821, "country_locode": "CN", "country_slug": "china", "city_locode": "KWE", "city": "Guigang", "city_slug": "guigang", "height_architecture_formatted": 75.9, "height_architecture_ft_formatted": "249", "floors_above": 24, "completed": 2016, "start": 2014, "structural_material": "", "functions": "residential", "retrofit_functions": "", "image": ""}]}