{"timestamp": "2019-Jan-20 15:57:45", "towers": [{"id": 14687, "url": "/building/lodha-bellezza-3/14687", "name": "Lodha Bellezza 3", "status": "COM", "height_architecture": 153, "longitude": 78.392639, "latitude": 17.47492, "rank": 1, "name_linked": "<a href='/building/lodha-bellezza-3/14687' target='_blank'>Lodha Bellezza 3</a>", "country_id": 75, "country_chinese": "", "city_id": 994, "country_locode": "IN", "country_slug": "india", "city_locode": "HYD", "city": "Hyderabad", "city_slug": "hyderabad", "height_architecture_formatted": 153, "height_architecture_ft_formatted": "502", "floors_above": 45, "completed": 2014, "start": "-", "structural_material": "concrete", "functions": "residential", "retrofit_functions": "", "image": ""}, {"id": 14688, "url": "/building/lodha-bellezza-4/14688", "name": "Lodha Bellezza 4", "status": "COM", "height_architecture": 153, "longitude": 78.393127, "latitude": 17.47456, "rank": 1, "name_linked": "<a href='/building/lodha-bellezza-4/14688' target='_blank'>Lodha Bellezza 4</a>", "country_id": 75, "country_chinese": "", "city_id": 994, "country_locode": "IN", "country_slug": "india", "city_locode": "HYD", "city": "Hyderabad", "city_slug": "hyderabad", "height_architecture_formatted": 153, "height_architecture_ft_formatted": "502", "floors_above": 45, "completed": 2014, "start": "-", "structural_material": "concrete", "functions": "residential", "retrofit_functions": "", "image": ""}, {"id": 16032, "url": "/building/lodha-bellezza-5/16032", "name": "Lodha Bellezza 5", "status": "COM", "height_architecture": 132, "longitude": 78.393639, "latitude": 17.47434, "rank": 3, "name_linked": "<a href='/building/lodha-bellezza-5/16032' target='_blank'>Lodha Bellezza 5</a>", "country_id": 75, "country_chinese": "", "city_id": 994, "country_locode": "IN", "country_slug": "india", "city_locode": "HYD", "city": "Hyderabad", "city_slug": "hyderabad", "height_architecture_formatted": 132, "height_architecture_ft_formatted": "433", "floors_above": 39, "completed": 2014, "start": "-", "structural_material": "concrete", "functions": "residential", "retrofit_functions": "", "image": ""}, {"id": 14689, "url": "/building/lodha-bellezza-1/14689", "name": "Lodha Bellezza 1", "status": "COM", "height_architecture": 115, "longitude": 78.392609, "latitude": 17.474001, "rank": 4, "name_linked": "<a href='/building/lodha-bellezza-1/14689' target='_blank'>Lodha Bellezza 1</a>", "country_id": 75, "country_chinese": "", "city_id": 994, "country_locode": "IN", "country_slug": "india", "city_locode": "HYD", "city": "Hyderabad", "city_slug": "hyderabad", "height_architecture_formatted": 115, "height_architecture_ft_formatted": "377", "floors_above": 32, "completed": 2014, "start": "-", "structural_material": "concrete", "functions": "residential", "retrofit_functions": "", "image": ""}, {"id": 14690, "url": "/building/lodha-bellezza-2/14690", "name": "Lodha Bellezza 2", "status": "COM", "height_architecture": 115, "longitude": 78.393257, "latitude": 17.473669, "rank": 4, "name_linked": "<a href='/building/lodha-bellezza-2/14690' target='_blank'>Lodha Bellezza 2</a>", "country_id": 75, "country_chinese": "", "city_id": 994, "country_locode": "IN", "country_slug": "india", "city_locode": "HYD", "city": "Hyderabad", "city_slug": "hyderabad", "height_architecture_formatted": 115, "height_architecture_ft_formatted": "377", "floors_above": 32, "completed": 2014, "start": "-", "structural_material": "concrete", "functions": "residential", "retrofit_functions": "", "image": ""}]}