{"timestamp": "2019-Jan-20 15:57:45", "towers": [{"id": 14033, "url": "/building/springfield-hilton/14033", "name": "Springfield Hilton", "status": "COM", "height_architecture": 107.3, "longitude": -89.645821, "latitude": 39.800171, "rank": 1, "name_linked": "<a href='/building/springfield-hilton/14033' target='_blank'>Springfield Hilton</a>", "country_id": 163, "country_chinese": "", "city_id": 1692, "country_locode": "US", "country_slug": "united-states", "city_locode": "SPI", "city": "Springfield (IL)", "city_slug": "springfield-il", "height_architecture_formatted": 107.3, "height_architecture_ft_formatted": "352", "floors_above": 30, "completed": 1973, "start": "-", "structural_material": "", "functions": "hotel", "retrofit_functions": "", "image": ""}]}