{"timestamp": "2019-Jan-20 15:57:45", "towers": [{"id": 10655, "url": "/building/wells-fargo-place/10655", "name": "Wells Fargo Place", "status": "COM", "height_architecture": 143.61, "longitude": -93.09552, "latitude": 44.948151, "rank": 1, "name_linked": "<a href='/building/wells-fargo-place/10655' target='_blank'>Wells Fargo Place</a>", "country_id": 163, "country_chinese": "", "city_id": 1694, "country_locode": "US", "country_slug": "united-states", "city_locode": "STP", "city": "St. Paul", "city_slug": "st-paul", "height_architecture_formatted": 143.6, "height_architecture_ft_formatted": "471", "floors_above": 37, "completed": 1987, "start": 1985, "structural_material": "concrete", "functions": "office", "retrofit_functions": "", "image": ""}, {"id": 10656, "url": "/building/jackson-tower/10656", "name": "Jackson Tower", "status": "COM", "height_architecture": 135, "longitude": -93.089859, "latitude": 44.948792, "rank": 2, "name_linked": "<a href='/building/jackson-tower/10656' target='_blank'>Jackson Tower</a>", "country_id": 163, "country_chinese": "", "city_id": 1694, "country_locode": "US", "country_slug": "united-states", "city_locode": "STP", "city": "St. Paul", "city_slug": "st-paul", "height_architecture_formatted": 135, "height_architecture_ft_formatted": "443", "floors_above": 46, "completed": 1986, "start": "-", "structural_material": "concrete", "functions": "residential", "retrofit_functions": "", "image": ""}, {"id": 10657, "url": "/building/first-national-bank-building/10657", "name": "First National Bank Building", "status": "COM", "height_architecture": 127.1, "longitude": -93.091217, "latitude": 44.946388, "rank": 3, "name_linked": "<a href='/building/first-national-bank-building/10657' target='_blank'>First National Bank Building</a>", "country_id": 163, "country_chinese": "", "city_id": 1694, "country_locode": "US", "country_slug": "united-states", "city_locode": "STP", "city": "St. Paul", "city_slug": "st-paul", "height_architecture_formatted": 127.1, "height_architecture_ft_formatted": "417", "floors_above": 32, "completed": 1931, "start": 1929, "structural_material": "steel", "functions": "office", "retrofit_functions": "", "image": ""}, {"id": 25671, "url": "/building/kellogg-square-apartments/25671", "name": "Kellogg Square Apartments", "status": "COM", "height_architecture": 111.6, "longitude": -93.090157, "latitude": 44.946121, "rank": 4, "name_linked": "<a href='/building/kellogg-square-apartments/25671' target='_blank'>Kellogg Square Apartments</a>", "country_id": 163, "country_chinese": "", "city_id": 1694, "country_locode": "US", "country_slug": "united-states", "city_locode": "STP", "city": "St. Paul", "city_slug": "st-paul", "height_architecture_formatted": 111.6, "height_architecture_ft_formatted": "366", "floors_above": 32, "completed": 1972, "start": 1970, "structural_material": "", "functions": "residential", "retrofit_functions": "", "image": ""}, {"id": 25674, "url": "/building/pointe-of-st-paul-condominiums/25674", "name": "Pointe of St. Paul Condominiums", "status": "COM", "height_architecture": 103.6, "longitude": -93.09594, "latitude": 44.950432, "rank": 5, "name_linked": "<a href='/building/pointe-of-st-paul-condominiums/25674' target='_blank'>Pointe of St. Paul Condominiums</a>", "country_id": 163, "country_chinese": "", "city_id": 1694, "country_locode": "US", "country_slug": "united-states", "city_locode": "STP", "city": "St. Paul", "city_slug": "st-paul", "height_architecture_formatted": 103.6, "height_architecture_ft_formatted": "340", "floors_above": 33, "completed": 1988, "start": 1986, "structural_material": "", "functions": "residential", "retrofit_functions": "", "image": ""}, {"id": 25670, "url": "/building/us-bank-building/25670", "name": "US Bank Building", "status": "COM", "height_architecture": 103.1, "longitude": -93.091682, "latitude": 44.947498, "rank": 6, "name_linked": "<a href='/building/us-bank-building/25670' target='_blank'>US Bank Building</a>", "country_id": 163, "country_chinese": "", "city_id": 1694, "country_locode": "US", "country_slug": "united-states", "city_locode": "STP", "city": "St. Paul", "city_slug": "st-paul", "height_architecture_formatted": 103.1, "height_architecture_ft_formatted": "338", "floors_above": 25, "completed": 1975, "start": "-", "structural_material": "", "functions": "office", "retrofit_functions": "", "image": ""}, {"id": 25676, "url": "/building/ecolab-building/25676", "name": "Ecolab Building", "status": "COM", "height_architecture": 100.6, "longitude": -93.098007, "latitude": 44.946709, "rank": 7, "name_linked": "<a href='/building/ecolab-building/25676' target='_blank'>Ecolab Building</a>", "country_id": 163, "country_chinese": "", "city_id": 1694, "country_locode": "US", "country_slug": "united-states", "city_locode": "STP", "city": "St. Paul", "city_slug": "st-paul", "height_architecture_formatted": 100.6, "height_architecture_ft_formatted": "330", "floors_above": 17, "completed": 1991, "start": 1988, "structural_material": "", "functions": "office", "retrofit_functions": "", "image": ""}, {"id": 25673, "url": "/building/bremer-tower/25673", "name": "Bremer Tower", "status": "COM", "height_architecture": 100, "longitude": -93.094391, "latitude": 44.948719, "rank": 8, "name_linked": "<a href='/building/bremer-tower/25673' target='_blank'>Bremer Tower</a>", "country_id": 163, "country_chinese": "", "city_id": 1694, "country_locode": "US", "country_slug": "united-states", "city_locode": "STP", "city": "St. Paul", "city_slug": "st-paul", "height_architecture_formatted": 100, "height_architecture_ft_formatted": "328", "floors_above": 27, "completed": 1980, "start": "-", "structural_material": "", "functions": "office", "retrofit_functions": "", "image": ""}, {"id": 25678, "url": "/building/the-400-building/25678", "name": "The 400 Building", "status": "COM", "height_architecture": 99.7, "longitude": -93.091629, "latitude": 44.94878, "rank": 9, "name_linked": "<a href='/building/the-400-building/25678' target='_blank'>The 400 Building</a>", "country_id": 163, "country_chinese": "", "city_id": 1694, "country_locode": "US", "country_slug": "united-states", "city_locode": "STP", "city": "St. Paul", "city_slug": "st-paul", "height_architecture_formatted": 99.7, "height_architecture_ft_formatted": "327", "floors_above": 21, "completed": 1982, "start": "-", "structural_material": "", "functions": "office", "retrofit_functions": "", "image": ""}, {"id": 25677, "url": "/building/landmark-tower/25677", "name": "Landmark Tower", "status": "COM", "height_architecture": 99.55, "longitude": -93.095871, "latitude": 44.944462, "rank": 10, "name_linked": "<a href='/building/landmark-tower/25677' target='_blank'>Landmark Tower</a>", "country_id": 163, "country_chinese": "", "city_id": 1694, "country_locode": "US", "country_slug": "united-states", "city_locode": "STP", "city": "St. Paul", "city_slug": "st-paul", "height_architecture_formatted": 99.6, "height_architecture_ft_formatted": "327", "floors_above": 26, "completed": 1983, "start": "-", "structural_material": "steel", "functions": "residential / office / retail", "retrofit_functions": "", "image": ""}, {"id": 25307, "url": "/building/sibley-tower/25307", "name": "Sibley Tower", "status": "COM", "height_architecture": 95.6, "longitude": -93.088821, "latitude": 44.948761, "rank": 11, "name_linked": "<a href='/building/sibley-tower/25307' target='_blank'>Sibley Tower</a>", "country_id": 163, "country_chinese": "", "city_id": 1694, "country_locode": "US", "country_slug": "united-states", "city_locode": "STP", "city": "St. Paul", "city_slug": "st-paul", "height_architecture_formatted": 95.6, "height_architecture_ft_formatted": "314", "floors_above": 33, "completed": 1986, "start": "-", "structural_material": "", "functions": "residential / office", "retrofit_functions": "", "image": ""}, {"id": 25716, "url": "/building/ecolab-corporate-center/25716", "name": "Ecolab Corporate Center", "status": "COM", "height_architecture": 93, "longitude": -93.094292, "latitude": 44.946171, "rank": 12, "name_linked": "<a href='/building/ecolab-corporate-center/25716' target='_blank'>Ecolab Corporate Center</a>", "country_id": 163, "country_chinese": "", "city_id": 1694, "country_locode": "US", "country_slug": "united-states", "city_locode": "STP", "city": "St. Paul", "city_slug": "st-paul", "height_architecture_formatted": 93, "height_architecture_ft_formatted": "305", "floors_above": 20, "completed": 1968, "start": "-", "structural_material": "", "functions": "office", "retrofit_functions": "", "image": ""}, {"id": 25672, "url": "/building/ubs-plaza/25672", "name": "UBS Plaza", "status": "COM", "height_architecture": 92.97, "longitude": -93.094856, "latitude": 44.94828, "rank": 13, "name_linked": "<a href='/building/ubs-plaza/25672' target='_blank'>UBS Plaza</a>", "country_id": 163, "country_chinese": "", "city_id": 1694, "country_locode": "US", "country_slug": "united-states", "city_locode": "STP", "city": "St. Paul", "city_slug": "st-paul", "height_architecture_formatted": 93, "height_architecture_ft_formatted": "305", "floors_above": 25, "completed": 1980, "start": "-", "structural_material": "concrete", "functions": "office", "retrofit_functions": "", "image": ""}, {"id": 25719, "url": "/building/custom-house/25719", "name": "Custom House", "status": "COM", "height_architecture": 83.52, "longitude": -93.087151, "latitude": 44.946621, "rank": 14, "name_linked": "<a href='/building/custom-house/25719' target='_blank'>Custom House</a>", "country_id": 163, "country_chinese": "", "city_id": 1694, "country_locode": "US", "country_slug": "united-states", "city_locode": "STP", "city": "St. Paul", "city_slug": "st-paul", "height_architecture_formatted": 83.5, "height_architecture_ft_formatted": "274", "floors_above": 17, "completed": 1939, "start": "-", "structural_material": "steel", "functions": "office / government", "retrofit_functions": "residential  / hotel", "image": ""}, {"id": 25721, "url": "/building/city-hall-courthouse/25721", "name": "City Hall & Courthouse", "status": "COM", "height_architecture": 79.5, "longitude": -93.093903, "latitude": 44.94413, "rank": 15, "name_linked": "<a href='/building/city-hall-courthouse/25721' target='_blank'>City Hall & Courthouse</a>", "country_id": 163, "country_chinese": "", "city_id": 1694, "country_locode": "US", "country_slug": "united-states", "city_locode": "STP", "city": "St. Paul", "city_slug": "st-paul", "height_architecture_formatted": 79.5, "height_architecture_ft_formatted": "261", "floors_above": 18, "completed": 1932, "start": 1931, "structural_material": "steel", "functions": "", "retrofit_functions": "", "image": ""}, {"id": 25722, "url": "/building/401-building/25722", "name": "401 Building", "status": "COM", "height_architecture": 78.13, "longitude": -93.092491, "latitude": 44.94846, "rank": 16, "name_linked": "<a href='/building/401-building/25722' target='_blank'>401 Building</a>", "country_id": 163, "country_chinese": "", "city_id": 1694, "country_locode": "US", "country_slug": "united-states", "city_locode": "STP", "city": "St. Paul", "city_slug": "st-paul", "height_architecture_formatted": 78.1, "height_architecture_ft_formatted": "256", "floors_above": 13, "completed": 2000, "start": 1998, "structural_material": "", "functions": "office / retail", "retrofit_functions": "", "image": ""}, {"id": 25723, "url": "/building/ecolab-university-center/25723", "name": "Ecolab University Center", "status": "COM", "height_architecture": 77.42, "longitude": -93.094887, "latitude": 44.946522, "rank": 17, "name_linked": "<a href='/building/ecolab-university-center/25723' target='_blank'>Ecolab University Center</a>", "country_id": 163, "country_chinese": "", "city_id": 1694, "country_locode": "US", "country_slug": "united-states", "city_locode": "STP", "city": "St. Paul", "city_slug": "st-paul", "height_architecture_formatted": 77.4, "height_architecture_ft_formatted": "254", "floors_above": 16, "completed": 1973, "start": 1972, "structural_material": "", "functions": "office", "retrofit_functions": "", "image": ""}]}